Workbook
Name campo: #REF!
Name campo: #REF!
Name campo: #REF!
Name Campo_Listagem: #REF!
Name Campo_Listagem: #REF!
Name Campo_Listagem: #REF!
Name Conteúdo: #REF!
Name FX_BRLEUR: #REF!
Name hj: #REF!
Name j: #REF!
Name periodo_selecionado: #REF!
Name PeriodoInPlanejado: #REF!=MEDIAN(#REF!,#REF!,#REF!+#REF!-1)
Name PeriodoInReal: #REF!=MEDIAN(#REF!,#REF!,#REF!+#REF!-1)
Name Plano: PeriodoInPlanejado*(#REF!>0)
Name PorcentagemConcluída: PorcentagemConcluídaPosterior*PeriodoInPlanejado
Name PorcentagemConcluídaPosterior: (#REF!=MEDIAN(#REF!,#REF!,#REF!+#REF!)*(#REF!>0))*((#REF!<(INT(#REF!+#REF!*#REF!)))+(#REF!=#REF!))*(#REF!>0)
Name Real: (PeriodoInReal*(#REF!>0))*PeriodoInPlanejado
Name RealPosterior: PeriodoInReal*(#REF!>0)
Name Resuumo: #REF!
Name Status: #REF!

Sheet RESUMO
D1: PLANILHA DE ESTIMATIVA DE CUSTOS
C2: Evento:
C3: Data do Evento:
C4: Horário do Evento:
C5: Data da Montagem:
C6: Qtde Pessoas:
C7: Local:
C8: PIT:
C9: Atendimento:
C10: Pré Produção:
I13: EXCLUIR NA VERSÃO CLIENTE | L13: EXCLUIR NA VERSÃO CLIENTE
B14: RESUMO GERAL | F14: CASHFLOW | I14: RENTABILIDADE _ BRUTO | L14: RENTABILIDADE _ LÍQUIDO
B15: PLANILHA | D15: VALOR | F15: À VISTA ANTECIPADO | G15: 30 DIAS | I15: MARGEM - R$ | J15: % | L15: MARGEM - R$ | M15: %
B16: GERAL | D16: =GERAL!I$428 -> 0 | F16: =GERAL!K$428 -> 0 | G16: =GERAL!L$428 -> 0 | I16: =GERAL!W424 -> 0 | J16: =GERAL!W425 -> #DIV/0! | L16: =GERAL!W427 -> 0 | M16: =GERAL!W428 -> #DIV/0!
D17: =SUM(D16:D16) -> 0 | F17: =SUM(F16:F16) -> 0 | G17: =SUM(G16:G16) -> 0
C20: BUDGET

Sheet GERAL
I2: PLANILHA DE ESTIMATIVA DE CUSTOS
H3: Evento: | I3: =RESUMO!D2 -> 0
H4: Data do Evento: | I4: =RESUMO!D3 -> 0
H5: Horário do Evento: | I5: =RESUMO!D4 -> 0
H6: Data da Montagem: | I6: =RESUMO!D5 -> 0
H7: Qtde Pessoas: | I7: =RESUMO!D6 -> 0
H8: Local: | I8: =RESUMO!D7 -> 0
H9: PIT: | I9: =RESUMO!D8 -> 0
H10: Atendimento: | I10: =RESUMO!D9 -> 0 | V10: TAXA BANCÁRIA POR MÊS | W10: 0.02 | AG10: TAXA BANCÁRIA POR MÊS
H11: Pré Produção: | I11: =RESUMO!D10 -> 0 | V11: VERIFICAR COM ATENDIMENTO COMO SERÁ COBRADO, DEPENDENDO DO CLIENTE
AG12: NÃO SE APLICA HONORÁRIOS
I13: =I428 -> 0
B14: ITEM | C14: DESCRIÇÃO | D14: INTERNO (I) TERCEIRO (T) CRIAÇÃO (C) | E14: QUANT | F14: UNIDADE | G14: VALOR UNIT | H14: VALOR TOTAL | I14: SUBTOTAL | K14: CASHFLOW | P14: Orçamentos | T14: PRÉ PRODUÇÃO | AC14: PRODUÇÃO
B15: 1 | C15: CRIAÇÃO E FINALIZAÇÃO | I15: =SUM(H16:H25) -> 0 | K15: À VISTA ANTECIPADO | L15: =RESUMO!G$15 -> 30 DIAS | P15: ORÇAMENTO 1 | Q15: ORÇAMENTO 2 | R15: ORÇAMENTO 3 | T15: FORNECEDOR | U15: CUSTO REAL | V15: TAXA BANCÁRIA | W15: SOBRA | X15: DEDUÇÃO DE IMPOSTO (FORNECEDOR) | Z15: PDI | AA15: TOTAL (SOBRA + PDI) | AC15: STATUS PRODUÇÃO | AD15: LINHA OC | AE15: FORNECEDOR | AF15: CUSTO REAL | AG15: TAXA BANCÁRIA | AH15: SOBRA | AI15: PDI | AJ15: TOTAL (SOBRA + PDI) | AK15: FECHAR ITEM | AL15: PRECISA DE NOTA DE COBERTURA? | AM15: DEDUÇÃO DE IMPOSTO (FORNECEDOR) | AO15: CÓDIGO FORNECEDOR - PUBLI | AP15: VENCIMENTO | AQ15: AUTORIZAÇÃO DE PRODUÇÃO ENVIADO
B16: 1.1 | C16: Desenvolvimento do KV e Conceito Criação e finalização. | D16: ( C ) | E16: 1 | F16: 1 | G16: 0 | H16: =E16*F16*G16 -> 0 | K16: 0 | L16: =H16 -> 0 | U16: 0 | V16: 0 | W16: =(H16-U16)-V16 -> 0 | X16: 1 | Y16: =W16-(W16*X16) -> 0 | Z16: =U16*0% -> 0 | AA16: =(W16+Z16)-Y16 -> 0 | AD16: =B16 -> 1.1 | AE16: =T16 -> 0 | AF16: =U16 -> 0 | AG16: 0 | AH16: =H16-AF16 -> 0 | AI16: =AF16*10% -> 0 | AJ16: =AN16+AI16 -> 0 | AK16: NÃO | AL16: NÃO | AM16: 0 | AN16: =(AH16-(AH16*AM16)) -> 0 | AP16: 0
B17: 1.2 | C17: Compra de imagens - VALIDAR COM CRIAÇÃO + ATENDIMENTO!!!!!!! A ser avaliado conforme desenvolvimento das peças. Valores apresentados posteriormente. | D17: ( I ) | E17: 1 | F17: 1 | G17: 0 | H17: =E17*F17*G17 -> 0 | K17: 0 | L17: =H17 -> 0 | U17: 0 | V17: 0 | W17: =(H17-U17)-V17 -> 0 | X17: 1 | Y17: =W17-(W17*X17) -> 0 | Z17: =U17*0% -> 0 | AA17: =(W17+Z17)-Y17 -> 0 | AD17: =B17 -> 1.2 | AE17: =T17 -> 0 | AF17: =U17 -> 0 | AG17: 0 | AH17: =H17-AF17 -> 0 | AI17: =AF17*10% -> 0 | AJ17: =AN17+AI17 -> 0 | AK17: NÃO | AL17: NÃO | AM17: 0 | AN17: =(AH17-(AH17*AM17)) -> 0 | AP17: 0
B18: 1.3 | C18: Peças de Comunicação Digital Criação e finalização das peças: Teaser, Save the date, convite, reminder 1 , reminder 2 e agradecimento. | D18: ( C ) | E18: 1 | F18: 1 | G18: 0 | H18: =E18*F18*G18 -> 0 | K18: 0 | L18: =H18 -> 0 | U18: 0 | V18: 0 | W18: =(H18-U18)-V18 -> 0 | X18: 1 | Y18: =W18-(W18*X18) -> 0 | Z18: =U18*0% -> 0 | AA18: =(W18+Z18)-Y18 -> 0 | AD18: =B18 -> 1.3 | AE18: =T18 -> 0 | AF18: =U18 -> 0 | AG18: 0 | AH18: =H18-AF18 -> 0 | AI18: =AF18*10% -> 0 | AJ18: =AN18+AI18 -> 0 | AK18: NÃO | AL18: NÃO | AM18: 0 | AN18: =(AH18-(AH18*AM18)) -> 0 | AP18: 0
B19: 1.4 | C19: Cenografia Criação e finalização de peças utilizadas na cenografia do evento. | D19: ( C ) | E19: 1 | F19: 1 | G19: 0 | H19: =E19*F19*G19 -> 0 | K19: 0 | L19: =H19 -> 0 | U19: 0 | V19: 0 | W19: =(H19-U19)-V19 -> 0 | X19: 1 | Y19: =W19-(W19*X19) -> 0 | Z19: =U19*0% -> 0 | AA19: =(W19+Z19)-Y19 -> 0 | AD19: =B19 -> 1.4 | AE19: =T19 -> 0 | AF19: =U19 -> 0 | AG19: 0 | AH19: =H19-AF19 -> 0 | AI19: =AF19*10% -> 0 | AJ19: =AN19+AI19 -> 0 | AK19: NÃO | AL19: NÃO | AM19: 0 | AN19: =(AH19-(AH19*AM19)) -> 0 | AP19: 0
B20: 1.5 | C20: Projeto Arquitetônico Projeto Arquitetônico / Design e Desenvolvimento em 3D | D20: ( C ) | E20: 1 | F20: 1 | G20: 0 | H20: =E20*F20*G20 -> 0 | K20: 0 | L20: =H20 -> 0 | U20: 0 | V20: 0 | W20: =(H20-U20)-V20 -> 0 | X20: 1 | Y20: =W20-(W20*X20) -> 0 | Z20: =U20*0% -> 0 | AA20: =(W20+Z20)-Y20 -> 0 | AD20: =B20 -> 1.5 | AE20: =T20 -> 0 | AF20: =U20 -> 0 | AG20: 0 | AH20: =H20-AF20 -> 0 | AI20: =AF20*10% -> 0 | AJ20: =AN20+AI20 -> 0 | AK20: NÃO | AL20: NÃO | AM20: 0 | AN20: =(AH20-(AH20*AM20)) -> 0 | AP20: 0
B21: 1.6 | C21: Template Criação e finalização de template para as apresentações. | D21: ( C ) | E21: 1 | F21: 1 | G21: 0 | H21: =E21*F21*G21 -> 0 | K21: 0 | L21: =H21 -> 0 | U21: 0 | V21: 0 | W21: =(H21-U21)-V21 -> 0 | X21: 1 | Y21: =W21-(W21*X21) -> 0 | Z21: =U21*0% -> 0 | AA21: =(W21+Z21)-Y21 -> 0 | AD21: =B21 -> 1.6 | AE21: =T21 -> 0 | AF21: =U21 -> 0 | AG21: 0 | AH21: =H21-AF21 -> 0 | AI21: =AF21*10% -> 0 | AJ21: =AN21+AI21 -> 0 | AK21: NÃO | AL21: NÃO | AM21: 0 | AN21: =(AH21-(AH21*AM21)) -> 0 | AP21: 0
B22: 1.7 | C22: Materiais Criação e finalização de brindes, uniforme e impressos | D22: ( C ) | E22: 1 | F22: 1 | G22: 0 | H22: =E22*F22*G22 -> 0 | K22: 0 | L22: =H22 -> 0 | U22: 0 | V22: 0 | W22: =(H22-U22)-V22 -> 0 | X22: 1 | Y22: =W22-(W22*X22) -> 0 | Z22: =U22*0% -> 0 | AA22: =(W22+Z22)-Y22 -> 0 | AD22: =B22 -> 1.7 | AE22: =T22 -> 0 | AF22: =U22 -> 0 | AG22: 0 | AH22: =H22-AF22 -> 0 | AI22: =AF22*10% -> 0 | AJ22: =AN22+AI22 -> 0 | AK22: NÃO | AL22: NÃO | AM22: 0 | AN22: =(AH22-(AH22*AM22)) -> 0 | AP22: 0
B23: 1.8 | C23: Retoque e/ou Tratamento de imagem | D23: ( C ) | E23: 1 | F23: 1 | G23: 0 | H23: =E23*F23*G23 -> 0 | K23: 0 | L23: =H23 -> 0 | U23: 0 | V23: 0 | W23: =(H23-U23)-V23 -> 0 | X23: 1 | Y23: =W23-(W23*X23) -> 0 | Z23: =U23*0% -> 0 | AA23: =(W23+Z23)-Y23 -> 0 | AD23: =B23 -> 1.8 | AE23: =T23 -> 0 | AF23: =U23 -> 0 | AG23: 0 | AH23: =H23-AF23 -> 0 | AI23: =AF23*10% -> 0 | AJ23: =AN23+AI23 -> 0 | AK23: NÃO | AL23: NÃO | AM23: 0 | AN23: =(AH23-(AH23*AM23)) -> 0 | AP23: 0
B24: 1.9 | C24: Ilustrações | D24: ( C ) | E24: 1 | F24: 1 | G24: 0 | H24: =E24*F24*G24 -> 0 | K24: 0 | L24: =H24 -> 0 | U24: 0 | V24: 0 | W24: =(H24-U24)-V24 -> 0 | X24: 1 | Y24: =W24-(W24*X24) -> 0 | Z24: =U24*0% -> 0 | AA24: =(W24+Z24)-Y24 -> 0 | AD24: =B24 -> 1.9 | AE24: =T24 -> 0 | AF24: =U24 -> 0 | AG24: 0 | AH24: =H24-AF24 -> 0 | AI24: =AF24*10% -> 0 | AJ24: =AN24+AI24 -> 0 | AK24: NÃO | AL24: NÃO | AM24: 0 | AN24: =(AH24-(AH24*AM24)) -> 0 | AP24: 0
B25: 1.10 | C25: Logo, elementos da marca e banco de imagens Disponibilidade de materiais gerais para realização do trabalho. | D25: ( T ) | E25: 1 | F25: 1 | G25: 0 | H25: RESPONSABILIDADE CLIENTE | K25: 0 | L25: =H25 -> RESPONSABILIDADE CLIENTE | T25: =L25 -> RESPONSABILIDADE CLIENTE | U25: 0 | V25: 0 | W25: 0 | X25: 1 | Y25: =W25-(W25*X25) -> 0 | Z25: =U25*0% -> 0 | AA25: =(W25+Z25)-Y25 -> 0 | AD25: =B25 -> 1.10 | AE25: =T25 -> RESPONSABILIDADE CLIENTE | AF25: =U25 -> 0 | AG25: 0 | AI25: =AF25*10% -> 0 | AJ25: =AN25+AI25 -> 0 | AK25: NÃO | AL25: NÃO | AM25: 0 | AN25: =(AH25-(AH25*AM25)) -> 0 | AP25: 0
B26: 2 | C26: COMUNICAÇÃO / RSVP / CREDENCIAMENTO | I26: =SUM(H27:H42) -> 0 | K26: À VISTA ANTECIPADO | L26: =L$15 -> 30 DIAS | P26: ORÇAMENTO 1 | Q26: ORÇAMENTO 2 | R26: ORÇAMENTO 3 | T26: FORNECEDOR | U26: CUSTO REAL | V26: TAXA BANCÁRIA | W26: SOBRA | X26: DEDUÇÃO DE IMPOSTO (FORNECEDOR) | Z26: PDI | AA26: TOTAL (SOBRA + PDI) | AC26: STATUS PRODUÇÃO | AD26: LINHA OC | AE26: FORNECEDOR | AF26: CUSTO REAL | AG26: TAXA BANCÁRIA | AH26: SOBRA | AI26: PDI | AJ26: TOTAL (SOBRA + PDI) | AK26: FECHAR ITEM | AL26: PRECISA DE NOTA DE COBERTURA? | AM26: DEDUÇÃO DE IMPOSTO (FORNECEDOR) | AO26: CÓDIGO FORNECEDOR - PUBLI | AP26: VENCIMENTO | AQ26: AUTORIZAÇÃO DE PRODUÇÃO ENVIADO
B27: 2.1 | C27: Mailing dos participantes Relação dos participantes do evento com a validação de suas presenças e dados necessários que serão alinhados no processo de produção do evento. | D27: ( T ) | E27: 1 | F27: 1 | G27: 0 | H27: RESPONSABILIDADE CLIENTE | K27: 0 | L27: =H27 -> RESPONSABILIDADE CLIENTE | T27: =L27 -> RESPONSABILIDADE CLIENTE | U27: 0 | V27: 0 | W27: 0 | X27: 1 | Y27: =W27-(W27*X27) -> 0 | Z27: =U27*10% -> 0 | AA27: =(W27+Z27)-Y27 -> 0 | AD27: =B27 -> 2.1 | AE27: =T27 -> RESPONSABILIDADE CLIENTE | AF27: =U27 -> 0 | AG27: 0 | AI27: =AF27*10% -> 0 | AJ27: =AN27+AI27 -> 0 | AK27: NÃO | AL27: NÃO | AM27: 0 | AN27: =(AH27-(AH27*AM27)) -> 0 | AP27: 0
B28: 2.2 | C28: Clean-up do mailing Prazo para recebimento: Valor sujeito a alteração sem aviso prévio. Caso o recebimento aconteça após a data sinalizado, valores poderão sofrer ajuste. Validade da proposta: XX dias à partir de xx/xx/xx. | D28: ( I ) | E28: 1 | F28: 1 | G28: 0 | H28: =E28*F28*G28 -> 0 | K28: 0 | L28: =H28 -> 0 | U28: 0 | V28: 0 | W28: =(H28-U28)-V28 -> 0 | X28: 1 | Y28: =W28-(W28*X28) -> 0 | Z28: =U28*10% -> 0 | AA28: =(W28+Z28)-Y28 -> 0 | AD28: =B28 -> 2.2 | AE28: =T28 -> 0 | AF28: =U28 -> 0 | AG28: 0 | AH28: =H28-AF28 -> 0 | AI28: =AF28*10% -> 0 | AJ28: =AN28+AI28 -> 0 | AK28: NÃO | AL28: NÃO | AM28: 0 | AN28: =(AH28-(AH28*AM28)) -> 0 | AP28: 0
B29: 2.3 | C29: Disparo de E-mail Marketing Prazo para aprovação: Prazo para configurações de sistema: Valor sujeito a alteração sem aviso prévio. Caso a aprovação aconteça após a data sinalizado, valores poderão sofrer ajuste. Validade da proposta: XX dias à partir de xx/xx/xx. | D29: ( I ) | E29: 1 | F29: 1 | G29: 0 | H29: =E29*F29*G29 -> 0 | K29: 0 | L29: =H29 -> 0 | U29: 0 | V29: 0 | W29: =(H29-U29)-V29 -> 0 | X29: 1 | Y29: =W29-(W29*X29) -> 0 | Z29: =U29*10% -> 0 | AA29: =(W29+Z29)-Y29 -> 0 | AD29: =B29 -> 2.3 | AE29: =T29 -> 0 | AF29: =U29 -> 0 | AG29: 0 | AH29: =H29-AF29 -> 0 | AI29: =AF29*10% -> 0 | AJ29: =AN29+AI29 -> 0 | AK29: NÃO | AL29: NÃO | AM29: 0 | AN29: =(AH29-(AH29*AM29)) -> 0 | AP29: 0
B30: 2.4 | C30: Disparo de Whatsapp Prazo para aprovação: Prazo para configurações de sistema: Valor sujeito a alteração sem aviso prévio. Caso a aprovação aconteça após a data sinalizado, valores poderão sofrer ajuste. Validade da proposta: XX dias à partir de xx/xx/xx. | D30: ( I ) | E30: 1 | F30: 1 | G30: 0 | H30: =E30*F30*G30 -> 0 | K30: 0 | L30: =H30 -> 0 | U30: 0 | V30: 0 | W30: =(H30-U30)-V30 -> 0 | X30: 1 | Y30: =W30-(W30*X30) -> 0 | Z30: =U30*10% -> 0 | AA30: =(W30+Z30)-Y30 -> 0 | AD30: =B30 -> 2.4 | AE30: =T30 -> 0 | AF30: =U30 -> 0 | AG30: 0 | AH30: =H30-AF30 -> 0 | AI30: =AF30*10% -> 0 | AJ30: =AN30+AI30 -> 0 | AK30: NÃO | AL30: NÃO | AM30: 0 | AN30: =(AH30-(AH30*AM30)) -> 0 | AP30: 0
B31: 2.5 | C31: Disparo de SMS Prazo para aprovação: Prazo para configurações de sistema: Valor sujeito a alteração sem aviso prévio. Caso a aprovação aconteça após a data sinalizado, valores poderão sofrer ajuste. Validade da proposta: XX dias à partir de xx/xx/xx. | D31: ( I ) | E31: 1 | F31: 1 | G31: 0 | H31: =E31*F31*G31 -> 0 | K31: 0 | L31: =H31 -> 0 | U31: 0 | V31: 0 | W31: =(H31-U31)-V31 -> 0 | X31: 1 | Y31: =W31-(W31*X31) -> 0 | Z31: =U31*10% -> 0 | AA31: =(W31+Z31)-Y31 -> 0 | AD31: =B31 -> 2.5 | AE31: =T31 -> 0 | AF31: =U31 -> 0 | AG31: 0 | AH31: =H31-AF31 -> 0 | AI31: =AF31*10% -> 0 | AJ31: =AN31+AI31 -> 0 | AK31: NÃO | AL31: NÃO | AM31: 0 | AN31: =(AH31-(AH31*AM31)) -> 0 | AP31: 0
B32: 2.6 | C32: Chatbot Prazo para aprovação: Prazo para configurações de sistema: Valor sujeito a alteração sem aviso prévio. Caso a aprovação aconteça após a data sinalizado, valores poderão sofrer ajuste. Validade da proposta: XX dias à partir de xx/xx/xx. | D32: ( I ) | E32: 1 | F32: 1 | G32: 0 | H32: =E32*F32*G32 -> 0 | K32: 0 | L32: =H32 -> 0 | U32: 0 | V32: 0 | W32: =(H32-U32)-V32 -> 0 | X32: 1 | Y32: =W32-(W32*X32) -> 0 | Z32: =U32*10% -> 0 | AA32: =(W32+Z32)-Y32 -> 0 | AD32: =B32 -> 2.6 | AE32: =T32 -> 0 | AF32: =U32 -> 0 | AG32: 0 | AH32: =H32-AF32 -> 0 | AI32: =AF32*10% -> 0 | AJ32: =AN32+AI32 -> 0 | AK32: NÃO | AL32: NÃO | AM32: 0 | AN32: =(AH32-(AH32*AM32)) -> 0 | AP32: 0
B33: 2.7 | C33: PA - Serviço Ativo Prazo para aprovação: Prazo para configurações de sistema: Valor sujeito a alteração sem aviso prévio. Caso a aprovação aconteça após a data sinalizado, valores poderão sofrer ajuste. Validade da proposta: XX dias à partir de xx/xx/xx. | D33: ( I ) | E33: 1 | F33: 1 | G33: 0 | H33: =E33*F33*G33 -> 0 | K33: 0 | L33: =H33 -> 0 | U33: 0 | V33: 0 | W33: =(H33-U33)-V33 -> 0 | X33: 1 | Y33: =W33-(W33*X33) -> 0 | Z33: =U33*10% -> 0 | AA33: =(W33+Z33)-Y33 -> 0 | AD33: =B33 -> 2.7 | AE33: =T33 -> 0 | AF33: =U33 -> 0 | AG33: 0 | AH33: =H33-AF33 -> 0 | AI33: =AF33*10% -> 0 | AJ33: =AN33+AI33 -> 0 | AK33: NÃO | AL33: NÃO | AM33: 0 | AN33: =(AH33-(AH33*AM33)) -> 0 | AP33: 0
B34: 2.8 | C34: PA - Serviço Receptivo Prazo para aprovação: Prazo para configurações de sistema: Valor sujeito a alteração sem aviso prévio. Caso a aprovação aconteça após a data sinalizado, valores poderão sofrer ajuste. Validade da proposta: XX dias à partir de xx/xx/xx. | D34: ( I ) | E34: 1 | F34: 1 | G34: 0 | H34: =E34*F34*G34 -> 0 | K34: 0 | L34: =H34 -> 0 | U34: 0 | V34: 0 | W34: =(H34-U34)-V34 -> 0 | X34: 1 | Y34: =W34-(W34*X34) -> 0 | Z34: =U34*10% -> 0 | AA34: =(W34+Z34)-Y34 -> 0 | AD34: =B34 -> 2.8 | AE34: =T34 -> 0 | AF34: =U34 -> 0 | AG34: 0 | AH34: =H34-AF34 -> 0 | AI34: =AF34*10% -> 0 | AJ34: =AN34+AI34 -> 0 | AK34: NÃO | AL34: NÃO | AM34: 0 | AN34: =(AH34-(AH34*AM34)) -> 0 | AP34: 0
B35: 2.9 | C35: Serviço Chatbot Prazo para aprovação: Prazo para configurações de sistema: Valor sujeito a alteração sem aviso prévio. Caso a aprovação aconteça após a data sinalizado, valores poderão sofrer ajuste. Validade da proposta: XX dias à partir de xx/xx/xx. | D35: ( I ) | E35: 1 | F35: 1 | G35: 0 | H35: =E35*F35*G35 -> 0 | K35: 0 | L35: =H35 -> 0 | U35: 0 | V35: 0 | W35: =(H35-U35)-V35 -> 0 | X35: 1 | Y35: =W35-(W35*X35) -> 0 | Z35: =U35*10% -> 0 | AA35: =(W35+Z35)-Y35 -> 0 | AD35: =B35 -> 2.9 | AE35: =T35 -> 0 | AF35: =U35 -> 0 | AG35: 0 | AH35: =H35-AF35 -> 0 | AI35: =AF35*10% -> 0 | AJ35: =AN35+AI35 -> 0 | AK35: NÃO | AL35: NÃO | AM35: 0 | AN35: =(AH35-(AH35*AM35)) -> 0 | AP35: 0
B36: 2.10 | C36: E-mail de agradecimento Prazo para aprovação: Prazo para configurações de sistema: Valor sujeito a alteração sem aviso prévio. Caso a aprovação aconteça após a data sinalizado, valores poderão sofrer ajuste. Validade da proposta: XX dias à partir de xx/xx/xx. | D36: ( I ) | E36: 1 | F36: 1 | G36: 0 | H36: =E36*F36*G36 -> 0 | K36: 0 | L36: =H36 -> 0 | U36: 0 | V36: 0 | W36: =(H36-U36)-V36 -> 0 | X36: 1 | Y36: =W36-(W36*X36) -> 0 | Z36: =U36*10% -> 0 | AA36: =(W36+Z36)-Y36 -> 0 | AD36: =B36 -> 2.10 | AE36: =T36 -> 0 | AF36: =U36 -> 0 | AG36: 0 | AH36: =H36-AF36 -> 0 | AI36: =AF36*10% -> 0 | AJ36: =AN36+AI36 -> 0 | AK36: NÃO | AL36: NÃO | AM36: 0 | AN36: =(AH36-(AH36*AM36)) -> 0 | AP36: 0
B37: 2.11 | C37: Pesquisa de Satisfação Prazo para aprovação: Prazo para configurações de sistema: Valor sujeito a alteração sem aviso prévio. Caso a aprovação aconteça após a data sinalizado, valores poderão sofrer ajuste. Validade da proposta: XX dias à partir de xx/xx/xx. | D37: ( I ) | E37: 1 | F37: 1 | G37: 0 | H37: =E37*F37*G37 -> 0 | K37: 0 | L37: =H37 -> 0 | U37: 0 | V37: 0 | W37: =(H37-U37)-V37 -> 0 | X37: 1 | Y37: =W37-(W37*X37) -> 0 | Z37: =U37*10% -> 0 | AA37: =(W37+Z37)-Y37 -> 0 | AD37: =B37 -> 2.11 | AE37: =T37 -> 0 | AF37: =U37 -> 0 | AG37: 0 | AH37: =H37-AF37 -> 0 | AI37: =AF37*10% -> 0 | AJ37: =AN37+AI37 -> 0 | AK37: NÃO | AL37: NÃO | AM37: 0 | AN37: =(AH37-(AH37*AM37)) -> 0 | AP37: 0
B38: 2.12 | C38: Hotsite / Landingpage / APP Prazo de produção: XX dias úteis à partir do recebimento da AF considerando a realziação de testes e validações de segurança. Valor sujeito a alteração sem aviso prévio. Caso a aprovação aconteça após a data sinalizado, valores poderão sofrer ajuste. Validade da proposta: XX dias à partir de xx/xx/xx. | D38: ( I ) | E38: 1 | F38: 1 | G38: 0 | H38: =E38*F38*G38 -> 0 | K38: 0 | L38: =H38 -> 0 | U38: 0 | V38: 0 | W38: =(H38-U38)-V38 -> 0 | X38: 1 | Y38: =W38-(W38*X38) -> 0 | Z38: =U38*10% -> 0 | AA38: =(W38+Z38)-Y38 -> 0 | AD38: =B38 -> 2.12 | AE38: =T38 -> 0 | AF38: =U38 -> 0 | AG38: 0 | AH38: =H38-AF38 -> 0 | AI38: =AF38*10% -> 0 | AJ38: =AN38+AI38 -> 0 | AK38: NÃO | AL38: NÃO | AM38: 0 | AN38: =(AH38-(AH38*AM38)) -> 0 | AP38: 0
B39: 2.13 | C39: QR Code Prazo de produção: XX dias úteis à partir do recebimento do link para direcionamento. Valor sujeito a alteração sem aviso prévio. Caso a aprovação e o recebimento do link aconteçam após a data sinalizado, valores poderão sofrer ajuste. Validade da proposta: XX dias à partir de xx/xx/xx. | D39: ( I ) | E39: 1 | F39: 1 | G39: 0 | H39: =E39*F39*G39 -> 0 | K39: 0 | L39: =H39 -> 0 | U39: 0 | V39: 0 | W39: =(H39-U39)-V39 -> 0 | X39: 1 | Y39: =W39-(W39*X39) -> 0 | Z39: =U39*10% -> 0 | AA39: =(W39+Z39)-Y39 -> 0 | AD39: =B39 -> 2.13 | AE39: =T39 -> 0 | AF39: =U39 -> 0 | AG39: 0 | AH39: =H39-AF39 -> 0 | AI39: =AF39*10% -> 0 | AJ39: =AN39+AI39 -> 0 | AK39: NÃO | AL39: NÃO | AM39: 0 | AN39: =(AH39-(AH39*AM39)) -> 0 | AP39: 0
... B42: 2.16 | C42: Promotoras Credenciamento Prazo para aprovação: Valor sujeito a alteração sem aviso prévio. Caso a aprovação aconteça após a data sinalizado, valores poderão sofrer ajuste. Validade da proposta: XX dias à partir de xx/xx/xx. | D42: ( I ) | E42: 1 | F42: 1 | G42: 0 | H42: =E42*F42*G42 -> 0 | K42: 0 | L42: =H42 -> 0 | U42: 0 | V42: 0 | W42: =(H42-U42)-V42 -> 0 | X42: 1 | Y42: =W42-(W42*X42) -> 0 | Z42: =U42*10% -> 0 | AA42: =(W42+Z42)-Y42 -> 0 | AD42: =B42 -> 2.16 | AE42: =T42 -> 0 | AF42: =U42 -> 0 | AG42: 0 | AH42: =H42-AF42 -> 0 | AI42: =AF42*10% -> 0 | AJ42: =AN42+AI42 -> 0 | AK42: NÃO | AL42: NÃO | AM42: 0 | AN42: =(AH42-(AH42*AM42)) -> 0 | AP42: 0
B43: 3 | C43: ESPAÇOS | I43: =SUM(H44:H54) -> 0 | K43: À VISTA ANTECIPADO | L43: =L$15 -> 30 DIAS | P43: ORÇAMENTO 1 | Q43: ORÇAMENTO 2 | R43: ORÇAMENTO 3 | T43: FORNECEDOR | U43: CUSTO REAL | V43: TAXA BANCÁRIA | W43: SOBRA | X43: DEDUÇÃO DE IMPOSTO (FORNECEDOR) | Z43: PDI | AA43: TOTAL (SOBRA + PDI) | AC43: STATUS PRODUÇÃO | AD43: LINHA OC | AE43: FORNECEDOR | AF43: CUSTO REAL | AG43: TAXA BANCÁRIA | AH43: SOBRA | AI43: PDI | AJ43: TOTAL (SOBRA + PDI) | AK43: FECHAR ITEM | AL43: PRECISA DE NOTA DE COBERTURA? | AM43: DEDUÇÃO DE IMPOSTO (FORNECEDOR) | AO43: CÓDIGO FORNECEDOR - PUBLI | AP43: VENCIMENTO | AQ43: AUTORIZAÇÃO DE PRODUÇÃO ENVIADO
B44: 3.1 | C44: Hotel - Locação de Salas Plenária Sujeito à disponibilidade para o período. Apenas cotação, sem realização de bloqueio. Consulta realizada em XX/XX/XX. Validade da proposta: XX dias à partir de xx/xx/xx. Valor sujeito a alteração sem aviso prévio. Forma de pagamento: | D44: ( I ) | E44: 1 | F44: 1 | G44: 0 | H44: =E44*F44*G44 -> 0 | K44: 0 | L44: =H44 -> 0 | U44: 0 | V44: 0 | W44: =(H44-U44)-V44 -> 0 | X44: 1 | Y44: =W44-(W44*X44) -> 0 | Z44: =U44*0% -> 0 | AA44: =(W44+Z44)-Y44 -> 0 | AD44: =B44 -> 3.1 | AE44: =T44 -> 0 | AF44: =U44 -> 0 | AG44: 0 | AH44: =H44-AF44 -> 0 | AI44: =AF44*10% -> 0 | AJ44: =AN44+AI44 -> 0 | AK44: NÃO | AL44: NÃO | AM44: 0 | AN44: =(AH44-(AH44*AM44)) -> 0 | AP44: 0
B45: 3.2 | C45: Hotel - Locação de Salas De apoio Sujeito à disponibilidade para o período. Apenas cotação, sem realização de bloqueio. Consulta realizada em XX/XX/XX. Validade da proposta: XX dias à partir de xx/xx/xx. Valor sujeito a alteração sem aviso prévio. Forma de pagamento: | D45: ( I ) | E45: 1 | F45: 1 | G45: 0 | H45: =E45*F45*G45 -> 0 | K45: 0 | L45: =H45 -> 0 | U45: 0 | V45: 0 | W45: =(H45-U45)-V45 -> 0 | X45: 1 | Y45: =W45-(W45*X45) -> 0 | Z45: =U45*0% -> 0 | AA45: =(W45+Z45)-Y45 -> 0 | AD45: =B45 -> 3.2 | AE45: =T45 -> 0 | AF45: =U45 -> 0 | AG45: 0 | AH45: =H45-AF45 -> 0 | AI45: =AF45*10% -> 0 | AJ45: =AN45+AI45 -> 0 | AK45: NÃO | AL45: NÃO | AM45: 0 | AN45: =(AH45-(AH45*AM45)) -> 0 | AP45: 0
B46: 3.3 | C46: Hotel - Locação de Foyer Sujeito à disponibilidade para o período. Apenas cotação, sem realização de bloqueio. Consulta realizada em XX/XX/XX. Validade da proposta: XX dias à partir de xx/xx/xx. Valor sujeito a alteração sem aviso prévio. Forma de pagamento: | D46: ( I ) | E46: 1 | F46: 1 | G46: 0 | H46: =E46*F46*G46 -> 0 | K46: 0 | L46: =H46 -> 0 | U46: 0 | V46: 0 | W46: =(H46-U46)-V46 -> 0 | X46: 1 | Y46: =W46-(W46*X46) -> 0 | Z46: =U46*0% -> 0 | AA46: =(W46+Z46)-Y46 -> 0 | AD46: =B46 -> 3.3 | AE46: =T46 -> 0 | AF46: =U46 -> 0 | AG46: 0 | AH46: =H46-AF46 -> 0 | AI46: =AF46*10% -> 0 | AJ46: =AN46+AI46 -> 0 | AK46: NÃO | AL46: NÃO | AM46: 0 | AN46: =(AH46-(AH46*AM46)) -> 0 | AP46: 0
B47: 3.4 | C47: Hotel - Locação de Sala de Reunião Sujeito à disponibilidade para o período. Apenas cotação, sem realização de bloqueio. Consulta realizada em XX/XX/XX. Validade da proposta: XX dias à partir de xx/xx/xx. Valor sujeito a alteração sem aviso prévio. Forma de pagamento: | D47: ( I ) | E47: 1 | F47: 1 | G47: 0 | H47: =E47*F47*G47 -> 0 | K47: 0 | L47: =H47 -> 0 | U47: 0 | V47: 0 | W47: =(H47-U47)-V47 -> 0 | X47: 1 | Y47: =W47-(W47*X47) -> 0 | Z47: =U47*0% -> 0 | AA47: =(W47+Z47)-Y47 -> 0 | AD47: =B47 -> 3.4 | AE47: =T47 -> 0 | AF47: =U47 -> 0 | AG47: 0 | AH47: =H47-AF47 -> 0 | AI47: =AF47*10% -> 0 | AJ47: =AN47+AI47 -> 0 | AK47: NÃO | AL47: NÃO | AM47: 0 | AN47: =(AH47-(AH47*AM47)) -> 0 | AP47: 0
B48: 3.5 | C48: Hotel - Locação de Espaços extras Sujeito à disponibilidade para o período. Apenas cotação, sem realização de bloqueio. Consulta realizada em XX/XX/XX. Validade da proposta: XX dias à partir de xx/xx/xx. Valor sujeito a alteração sem aviso prévio. Forma de pagamento: | D48: ( I ) | E48: 1 | F48: 1 | G48: 0 | H48: =E48*F48*G48 -> 0 | K48: 0 | L48: =H48 -> 0 | U48: 0 | V48: 0 | W48: =(H48-U48)-V48 -> 0 | X48: 1 | Y48: =W48-(W48*X48) -> 0 | Z48: =U48*0% -> 0 | AA48: =(W48+Z48)-Y48 -> 0 | AD48: =B48 -> 3.5 | AE48: =T48 -> 0 | AF48: =U48 -> 0 | AG48: 0 | AH48: =H48-AF48 -> 0 | AI48: =AF48*10% -> 0 | AJ48: =AN48+AI48 -> 0 | AK48: NÃO | AL48: NÃO | AM48: 0 | AN48: =(AH48-(AH48*AM48)) -> 0 | AP48: 0
B49: 3.6 | C49: Hotel - Locação de Espaços extras (sala de produção, camarim, estoque) Sujeito à disponibilidade para o período. Apenas cotação, sem realização de bloqueio. Consulta realizada em XX/XX/XX. Validade da proposta: XX dias à partir de xx/xx/xx. Valor sujeito a alteração sem aviso prévio. Forma de pagamento: | D49: ( I ) | E49: 1 | F49: 1 | G49: 0 | H49: =E49*F49*G49 -> 0 | K49: 0 | L49: =H49 -> 0 | U49: 0 | V49: 0 | W49: =(H49-U49)-V49 -> 0 | X49: 1 | Y49: =W49-(W49*X49) -> 0 | Z49: =U49*0% -> 0 | AA49: =(W49+Z49)-Y49 -> 0 | AD49: =B49 -> 3.6 | AE49: =T49 -> 0 | AF49: =U49 -> 0 | AG49: 0 | AH49: =H49-AF49 -> 0 | AI49: =AF49*10% -> 0 | AJ49: =AN49+AI49 -> 0 | AK49: NÃO | AL49: NÃO | AM49: 0 | AN49: =(AH49-(AH49*AM49)) -> 0 | AP49: 0
B50: 3.7 | C50: Espaço e eventos Sujeito à disponibilidade para o período. Apenas cotação, sem realização de bloqueio. Consulta realizada em XX/XX/XX. Validade da proposta: XX dias à partir de xx/xx/xx. Valor sujeito a alteração sem aviso prévio. Forma de pagamento: | D50: ( I ) | E50: 1 | F50: 1 | G50: 0 | H50: =E50*F50*G50 -> 0 | K50: 0 | L50: =H50 -> 0 | U50: 0 | V50: 0 | W50: =(H50-U50)-V50 -> 0 | X50: 1 | Y50: =W50-(W50*X50) -> 0 | Z50: =U50*0% -> 0 | AA50: =(W50+Z50)-Y50 -> 0 | AD50: =B50 -> 3.7 | AE50: =T50 -> 0 | AF50: =U50 -> 0 | AG50: 0 | AH50: =H50-AF50 -> 0 | AI50: =AF50*10% -> 0 | AJ50: =AN50+AI50 -> 0 | AK50: NÃO | AL50: NÃO | AM50: 0 | AN50: =(AH50-(AH50*AM50)) -> 0 | AP50: 0
B51: 3.8 | C51: Taxas Sobre a Locação do Espaço Consulta realizada em XX/XX/XX. Validade da proposta: XX dias à partir de xx/xx/xx. Valor sujeito a alteração sem aviso prévio: Forma de pagamento: | D51: ( I ) | E51: 1 | F51: 1 | G51: 0 | H51: =E51*F51*G51 -> 0 | K51: =H51 -> 0 | L51: 0 | U51: 0 | V51: 0 | W51: =(H51-U51)-V51 -> 0 | X51: 1 | Y51: =W51-(W51*X51) -> 0 | Z51: =U51*0% -> 0 | AA51: =(W51+Z51)-Y51 -> 0 | AD51: =B51 -> 3.8 | AE51: =T51 -> 0 | AF51: =U51 -> 0 | AG51: 0 | AH51: =H51-AF51 -> 0 | AI51: =AF51*10% -> 0 | AJ51: =AN51+AI51 -> 0 | AK51: NÃO | AL51: NÃO | AM51: 0 | AN51: =(AH51-(AH51*AM51)) -> 0 | AP51: 0
B52: 3.9 | C52: Shopping - Loja, quiosque Sujeito à disponibilidade para o período. Apenas cotação, sem realização de bloqueio. Consulta realizada em XX/XX/XX. Validade da proposta: XX dias à partir de xx/xx/xx. Valor sujeito a alteração sem aviso prévio. Forma de pagamento: | D52: ( I ) | E52: 1 | F52: 1 | G52: 0 | H52: =E52*F52*G52 -> 0 | K52: =H52 -> 0 | L52: 0 | U52: 0 | V52: 0 | W52: =(H52-U52)-V52 -> 0 | X52: 1 | Y52: =W52-(W52*X52) -> 0 | Z52: =U52*0% -> 0 | AA52: =(W52+Z52)-Y52 -> 0 | AD52: =B52 -> 3.9 | AE52: =T52 -> 0 | AF52: =U52 -> 0 | AG52: 0 | AH52: =H52-AF52 -> 0 | AI52: =AF52*10% -> 0 | AJ52: =AN52+AI52 -> 0 | AK52: NÃO | AL52: NÃO | AM52: 0 | AN52: =(AH52-(AH52*AM52)) -> 0 | AP52: 0
B53: 3.10 | C53: Espaço público Sujeito à disponibilidade para o período. Apenas cotação, sem realização de bloqueio. Consulta realizada em XX/XX/XX. Validade da proposta: XX dias à partir de xx/xx/xx. Valor sujeito a alteração sem aviso prévio. Forma de pagamento: | D53: ( I ) | E53: 1 | F53: 1 | G53: 0 | H53: =E53*F53*G53 -> 0 | K53: =H53 -> 0 | L53: 0 | U53: 0 | V53: 0 | W53: =(H53-U53)-V53 -> 0 | X53: 1 | Y53: =W53-(W53*X53) -> 0 | Z53: =U53*0% -> 0 | AA53: =(W53+Z53)-Y53 -> 0 | AD53: =B53 -> 3.10 | AE53: =T53 -> 0 | AF53: =U53 -> 0 | AG53: 0 | AH53: =H53-AF53 -> 0 | AI53: =AF53*10% -> 0 | AJ53: =AN53+AI53 -> 0 | AK53: NÃO | AL53: NÃO | AM53: 0 | AN53: =(AH53-(AH53*AM53)) -> 0 | AP53: 0
B54: 3.11 | C54: Empena Sujeito à disponibilidade para o período. Apenas cotação, sem realização de bloqueio. Consulta realizada em XX/XX/XX. Validade da proposta: XX dias à partir de xx/xx/xx. Valor sujeito a alteração sem aviso prévio. Forma de pagamento: | D54: ( I ) | E54: 1 | F54: 1 | G54: 0 | H54: =E54*F54*G54 -> 0 | K54: =H54 -> 0 | L54: 0 | U54: 0 | V54: 0 | W54: =(H54-U54)-V54 -> 0 | X54: 1 | Y54: =W54-(W54*X54) -> 0 | Z54: =U54*0% -> 0 | AA54: =(W54+Z54)-Y54 -> 0 | AD54: =B54 -> 3.11 | AE54: =T54 -> 0 | AF54: =U54 -> 0 | AG54: 0 | AH54: =H54-AF54 -> 0 | AI54: =AF54*10% -> 0 | AJ54: =AN54+AI54 -> 0 | AK54: NÃO | AL54: NÃO | AM54: 0 | AN54: =(AH54-(AH54*AM54)) -> 0 | AP54: 0
B55: 4 | C55: CENOGRAFIA / DECORAÇÃO | I55: =SUM(H56:H81) -> 0 | K55: À VISTA ANTECIPADO | L55: =L$15 -> 30 DIAS | P55: ORÇAMENTO 1 | Q55: ORÇAMENTO 2 | R55: ORÇAMENTO 3 | T55: FORNECEDOR | U55: CUSTO REAL | V55: TAXA BANCÁRIA | W55: SOBRA | X55: DEDUÇÃO DE IMPOSTO (FORNECEDOR) | Z55: PDI | AA55: TOTAL (SOBRA + PDI) | AC55: STATUS PRODUÇÃO | AD55: LINHA OC | AE55: FORNECEDOR | AF55: CUSTO REAL | AG55: TAXA BANCÁRIA | AH55: SOBRA | AI55: PDI | AJ55: TOTAL (SOBRA + PDI) | AK55: FECHAR ITEM | AL55: PRECISA DE NOTA DE COBERTURA? | AM55: DEDUÇÃO DE IMPOSTO (FORNECEDOR) | AO55: CÓDIGO FORNECEDOR - PUBLI | AP55: VENCIMENTO | AQ55: AUTORIZAÇÃO DE PRODUÇÃO ENVIADO
B56: 4.1 | C56: Cenografia Valor sujeito a alteração após realização da visita técnica. Prazo para produção: Valores poderão sofrer ajustes em caso de alteração do escopo do projeto após apresentação. | D56: ( I ) | E56: 1 | F56: 1 | G56: 0 | H56: =E56*F56*G56 -> 0 | K56: 0 | L56: =H56 -> 0 | U56: 0 | V56: 0 | W56: =(H56-U56)-V56 -> 0 | X56: 1 | Y56: =W56-(W56*X56) -> 0 | Z56: =U56*10% -> 0 | AA56: =(W56+Z56)-Y56 -> 0 | AD56: =B56 -> 4.1 | AE56: =T56 -> 0 | AF56: =U56 -> 0 | AG56: 0 | AH56: =H56-AF56 -> 0 | AI56: =AF56*10% -> 0 | AJ56: =AN56+AI56 -> 0 | AK56: NÃO | AL56: NÃO | AM56: 0 | AN56: =(AH56-(AH56*AM56)) -> 0 | AP56: 0
B57: 4.2 | C57: Dog House Valor sujeito a alteração após realização da visita técnica. Prazo para produção: Valores poderão sofrer ajustes em caso de alteração do escopo do projeto após apresentação. | D57: ( I ) | E57: 1 | F57: 1 | G57: 0 | H57: =E57*F57*G57 -> 0 | K57: 0 | L57: =H57 -> 0 | U57: 0 | V57: 0 | W57: =(H57-U57)-V57 -> 0 | X57: 1 | Y57: =W57-(W57*X57) -> 0 | Z57: =U57*10% -> 0 | AA57: =(W57+Z57)-Y57 -> 0 | AD57: =B57 -> 4.2 | AE57: =T57 -> 0 | AF57: =U57 -> 0 | AG57: 0 | AH57: =H57-AF57 -> 0 | AI57: =AF57*10% -> 0 | AJ57: =AN57+AI57 -> 0 | AK57: NÃO | AL57: NÃO | AM57: 0 | AN57: =(AH57-(AH57*AM57)) -> 0 | AP57: 0
B58: 4.3 | C58: House Mix Valor sujeito a alteração após realização da visita técnica. Prazo para produção: Valores poderão sofrer ajustes em caso de alteração do escopo do projeto após apresentação. | D58: ( I ) | E58: 1 | F58: 1 | G58: 0 | H58: =E58*F58*G58 -> 0 | K58: 0 | L58: =H58 -> 0 | U58: 0 | V58: 0 | W58: =(H58-U58)-V58 -> 0 | X58: 1 | Y58: =W58-(W58*X58) -> 0 | Z58: =U58*10% -> 0 | AA58: =(W58+Z58)-Y58 -> 0 | AD58: =B58 -> 4.3 | AE58: =T58 -> 0 | AF58: =U58 -> 0 | AG58: 0 | AH58: =H58-AF58 -> 0 | AI58: =AF58*10% -> 0 | AJ58: =AN58+AI58 -> 0 | AK58: NÃO | AL58: NÃO | AM58: 0 | AN58: =(AH58-(AH58*AM58)) -> 0 | AP58: 0
B59: 4.4 | C59: Pranchão e cadeira para house mix Modelo e cor sujeito à disponibilidade em estoque. Quantidades e valor poderão sofrer ajuste após realziação de visita técnica. Prazo para aprovação: | D59: ( I ) | E59: 1 | F59: 1 | G59: 0 | H59: =E59*F59*G59 -> 0 | K59: 0 | L59: =H59 -> 0 | U59: 0 | V59: 0 | W59: =(H59-U59)-V59 -> 0 | X59: 1 | Y59: =W59-(W59*X59) -> 0 | Z59: =U59*10% -> 0 | AA59: =(W59+Z59)-Y59 -> 0 | AD59: =B59 -> 4.4 | AE59: =T59 -> 0 | AF59: =U59 -> 0 | AG59: 0 | AH59: =H59-AF59 -> 0 | AI59: =AF59*10% -> 0 | AJ59: =AN59+AI59 -> 0 | AK59: NÃO | AL59: NÃO | AM59: 0 | AN59: =(AH59-(AH59*AM59)) -> 0 | AP59: 0
B60: 4.5 | C60: Acabamento ribaltas (Protetor em madeira para esconder os spots de iluminação ) Valor sujeito a alteração após realização da visita técnica. Prazo para produção: Valores poderão sofrer ajustes em caso de alteração do escopo do projeto após apresentação. | D60: ( I ) | E60: 1 | F60: 1 | G60: 0 | H60: =E60*F60*G60 -> 0 | K60: 0 | L60: =H60 -> 0 | U60: 0 | V60: 0 | W60: =(H60-U60)-V60 -> 0 | X60: 1 | Y60: =W60-(W60*X60) -> 0 | Z60: =U60*10% -> 0 | AA60: =(W60+Z60)-Y60 -> 0 | AD60: =B60 -> 4.5 | AE60: =T60 -> 0 | AF60: =U60 -> 0 | AG60: 0 | AH60: =H60-AF60 -> 0 | AI60: =AF60*10% -> 0 | AJ60: =AN60+AI60 -> 0 | AK60: NÃO | AL60: NÃO | AM60: 0 | AN60: =(AH60-(AH60*AM60)) -> 0 | AP60: 0
B61: 4.6 | C61: ART Elétrica + ART Estudo Estrutural/Carga Valor sujeito a alteração em caso de ajustes/adaptações do projeto. Prazo para aprovação: | D61: ( I ) | E61: 1 | F61: 1 | G61: 0 | H61: =E61*F61*G61 -> 0 | K61: 0 | L61: =H61 -> 0 | U61: 0 | V61: 0 | W61: =(H61-U61)-V61 -> 0 | X61: 1 | Y61: =W61-(W61*X61) -> 0 | Z61: =U61*10% -> 0 | AA61: =(W61+Z61)-Y61 -> 0 | AD61: =B61 -> 4.6 | AE61: =T61 -> 0 | AF61: =U61 -> 0 | AG61: 0 | AH61: =H61-AF61 -> 0 | AI61: =AF61*10% -> 0 | AJ61: =AN61+AI61 -> 0 | AK61: NÃO | AL61: NÃO | AM61: 0 | AN61: =(AH61-(AH61*AM61)) -> 0 | AP61: 0
B62: 4.7 | C62: Chapeamento Valor sujeito a alteração após realização da visita técnica. Prazo para produção: Valores poderão sofrer ajustes em caso de alteração do escopo do projeto após apresentação. | D62: ( I ) | E62: 1 | F62: 1 | G62: 0 | H62: =E62*F62*G62 -> 0 | K62: 0 | L62: =H62 -> 0 | U62: 0 | V62: 0 | W62: =(H62-U62)-V62 -> 0 | X62: 1 | Y62: =W62-(W62*X62) -> 0 | Z62: =U62*10% -> 0 | AA62: =(W62+Z62)-Y62 -> 0 | AD62: =B62 -> 4.7 | AE62: =T62 -> 0 | AF62: =U62 -> 0 | AG62: 0 | AH62: =H62-AF62 -> 0 | AI62: =AF62*10% -> 0 | AJ62: =AN62+AI62 -> 0 | AK62: NÃO | AL62: NÃO | AM62: 0 | AN62: =(AH62-(AH62*AM62)) -> 0 | AP62: 0
B63: 4.8 | C63: Revestimento em lycra / malha tensionada Valor sujeito a alteração após realização da visita técnica. Prazo para aprovação: Valores poderão sofrer ajustes em caso de alteração do escopo do projeto após apresentação. | D63: ( I ) | E63: 1 | F63: 1 | G63: 0 | H63: =E63*F63*G63 -> 0 | K63: 0 | L63: =H63 -> 0 | U63: 0 | V63: 0 | W63: =(H63-U63)-V63 -> 0 | X63: 1 | Y63: =W63-(W63*X63) -> 0 | Z63: =U63*10% -> 0 | AA63: =(W63+Z63)-Y63 -> 0 | AD63: =B63 -> 4.8 | AE63: =T63 -> 0 | AF63: =U63 -> 0 | AG63: 0 | AH63: =H63-AF63 -> 0 | AI63: =AF63*10% -> 0 | AJ63: =AN63+AI63 -> 0 | AK63: NÃO | AL63: NÃO | AM63: 0 | AN63: =(AH63-(AH63*AM63)) -> 0 | AP63: 0
B64: 4.9 | C64: Piso elevado / tablado Valor sujeito a alteração após realização da visita técnica. Prazo para produção: Valores poderão sofrer ajustes em caso de alteração do escopo do projeto após apresentação. | D64: ( I ) | E64: 1 | F64: 1 | G64: 0 | H64: =E64*F64*G64 -> 0 | K64: 0 | L64: =H64 -> 0 | U64: 0 | V64: 0 | W64: =(H64-U64)-V64 -> 0 | X64: 1 | Y64: =W64-(W64*X64) -> 0 | Z64: =U64*10% -> 0 | AA64: =(W64+Z64)-Y64 -> 0 | AD64: =B64 -> 4.9 | AE64: =T64 -> 0 | AF64: =U64 -> 0 | AG64: 0 | AH64: =H64-AF64 -> 0 | AI64: =AF64*10% -> 0 | AJ64: =AN64+AI64 -> 0 | AK64: NÃO | AL64: NÃO | AM64: 0 | AN64: =(AH64-(AH64*AM64)) -> 0 | AP64: 0
B65: 4.10 | C65: Nivelamento de Piso Valor sujeito a alteração após realização da visita técnica. Prazo para aprovação: Valores poderão sofrer ajustes em caso de alteração do escopo do projeto após apresentação. | D65: ( I ) | E65: 1 | F65: 1 | G65: 0 | H65: =E65*F65*G65 -> 0 | K65: 0 | L65: =H65 -> 0 | U65: 0 | V65: 0 | W65: =(H65-U65)-V65 -> 0 | X65: 1 | Y65: =W65-(W65*X65) -> 0 | Z65: =U65*10% -> 0 | AA65: =(W65+Z65)-Y65 -> 0 | AD65: =B65 -> 4.10 | AE65: =T65 -> 0 | AF65: =U65 -> 0 | AG65: 0 | AH65: =H65-AF65 -> 0 | AI65: =AF65*10% -> 0 | AJ65: =AN65+AI65 -> 0 | AK65: NÃO | AL65: NÃO | AM65: 0 | AN65: =(AH65-(AH65*AM65)) -> 0 | AP65: 0
B66: 4.11 | C66: Rampa de acesso Valor sujeito a alteração após realização da visita técnica. Prazo para aprovação: Valores poderão sofrer ajustes em caso de alteração do escopo do projeto após apresentação. | D66: ( I ) | E66: 1 | F66: 1 | G66: 0 | H66: =E66*F66*G66 -> 0 | K66: 0 | L66: =H66 -> 0 | U66: 0 | V66: 0 | W66: =(H66-U66)-V66 -> 0 | X66: 1 | Y66: =W66-(W66*X66) -> 0 | Z66: =U66*10% -> 0 | AA66: =(W66+Z66)-Y66 -> 0 | AD66: =B66 -> 4.11 | AE66: =T66 -> 0 | AF66: =U66 -> 0 | AG66: 0 | AH66: =H66-AF66 -> 0 | AI66: =AF66*10% -> 0 | AJ66: =AN66+AI66 -> 0 | AK66: NÃO | AL66: NÃO | AM66: 0 | AN66: =(AH66-(AH66*AM66)) -> 0 | AP66: 0
B67: 4.12 | C67: Acabamento Piso (forração, easy floor, palet recapeadoetc) Valor sujeito a alteração após realização da visita técnica. Prazo para aprovação: Valores poderão sofrer ajustes em caso de alteração do escopo do projeto após apresentação. | D67: ( I ) | E67: 1 | F67: 1 | G67: 0 | H67: =E67*F67*G67 -> 0 | K67: 0 | L67: =H67 -> 0 | U67: 0 | V67: 0 | W67: =(H67-U67)-V67 -> 0 | X67: 1 | Y67: =W67-(W67*X67) -> 0 | Z67: =U67*10% -> 0 | AA67: =(W67+Z67)-Y67 -> 0 | AD67: =B67 -> 4.12 | AE67: =T67 -> 0 | AF67: =U67 -> 0 | AG67: 0 | AH67: =H67-AF67 -> 0 | AI67: =AF67*10% -> 0 | AJ67: =AN67+AI67 -> 0 | AK67: NÃO | AL67: NÃO | AM67: 0 | AN67: =(AH67-(AH67*AM67)) -> 0 | AP67: 0
B68: 4.13 | C68: Ignifugação Valor sujeito a alteração após realização da visita técnica. Prazo para aprovação: Valores poderão sofrer ajustes em caso de alteração do escopo do projeto após apresentação. | D68: ( I ) | E68: 1 | F68: 1 | G68: 0 | H68: =E68*F68*G68 -> 0 | K68: 0 | L68: =H68 -> 0 | U68: 0 | V68: 0 | W68: =(H68-U68)-V68 -> 0 | X68: 1 | Y68: =W68-(W68*X68) -> 0 | Z68: =U68*10% -> 0 | AA68: =(W68+Z68)-Y68 -> 0 | AD68: =B68 -> 4.13 | AE68: =T68 -> 0 | AF68: =U68 -> 0 | AG68: 0 | AH68: =H68-AF68 -> 0 | AI68: =AF68*10% -> 0 | AJ68: =AN68+AI68 -> 0 | AK68: NÃO | AL68: NÃO | AM68: 0 | AN68: =(AH68-(AH68*AM68)) -> 0 | AP68: 0
C69: DECORAÇÃO
B70: 4.14 | C70: Locação de mobiliário Evento Valor sujeito a alteração sem aviso prévio. Sujeito à disponibilidade em estoque de modelo e cores. Prazo para aprovação: Sem realização de pré reserva sem a realização do pagamento de sinal ou assinatura do contrato. | D70: ( I ) | E70: 1 | F70: 1 | G70: 0 | H70: =E70*F70*G70 -> 0 | K70: 0 | L70: =H70 -> 0 | U70: 0 | V70: 0 | W70: =(H70-U70)-V70 -> 0 | X70: 1 | Y70: =W70-(W70*X70) -> 0 | Z70: =U70*10% -> 0 | AA70: =(W70+Z70)-Y70 -> 0 | AD70: =B70 -> 4.14 | AE70: =T70 -> 0 | AF70: =U70 -> 0 | AG70: 0 | AH70: =H70-AF70 -> 0 | AI70: =AF70*10% -> 0 | AJ70: =AN70+AI70 -> 0 | AK70: NÃO | AL70: NÃO | AM70: 0 | AN70: =(AH70-(AH70*AM70)) -> 0 | AP70: 0
B71: 4.15 | C71: Locação de mobiliário Camarim Valor sujeito a alteração sem aviso prévio. Sujeito à disponibilidade em estoque de modelo e cores. Prazo para aprovação: Sem realização de pré reserva sem a realização do pagamento de sinal ou assinatura do contrato. | D71: ( I ) | E71: 1 | F71: 1 | G71: 0 | H71: =E71*F71*G71 -> 0 | K71: 0 | L71: =H71 -> 0 | U71: 0 | V71: 0 | W71: =(H71-U71)-V71 -> 0 | X71: 1 | Y71: =W71-(W71*X71) -> 0 | Z71: =U71*10% -> 0 | AA71: =(W71+Z71)-Y71 -> 0 | AD71: =B71 -> 4.15 | AE71: =T71 -> 0 | AF71: =U71 -> 0 | AG71: 0 | AH71: =H71-AF71 -> 0 | AI71: =AF71*10% -> 0 | AJ71: =AN71+AI71 -> 0 | AK71: NÃO | AL71: NÃO | AM71: 0 | AN71: =(AH71-(AH71*AM71)) -> 0 | AP71: 0
B72: 4.16 | C72: Locação de mobiliário House Mix Valor sujeito a alteração sem aviso prévio. Sujeito à disponibilidade em estoque de modelo e cores. Prazo para aprovação: Sem realização de pré reserva sem a realização do pagamento de sinal ou assinatura do contrato. | D72: ( I ) | E72: 1 | F72: 1 | G72: 0 | H72: =E72*F72*G72 -> 0 | K72: 0 | L72: =H72 -> 0 | U72: 0 | V72: 0 | W72: =(H72-U72)-V72 -> 0 | X72: 1 | Y72: =W72-(W72*X72) -> 0 | Z72: =U72*10% -> 0 | AA72: =(W72+Z72)-Y72 -> 0 | AD72: =B72 -> 4.16 | AE72: =T72 -> 0 | AF72: =U72 -> 0 | AG72: 0 | AH72: =H72-AF72 -> 0 | AI72: =AF72*10% -> 0 | AJ72: =AN72+AI72 -> 0 | AK72: NÃO | AL72: NÃO | AM72: 0 | AN72: =(AH72-(AH72*AM72)) -> 0 | AP72: 0
B73: 4.17 | C73: Mobiliário hotel - House mix Cadeiras, pranchões, toalhas sob responsabilidade do hotel. Valor sujeito a alteração sem aviso prévio. Sujeito à disponibilidade em estoque de modelo e cores. Prazo para aprovação: Sem realização de pré reserva sem a realização do pagamento de sinal ou assinatura do contrato. | D73: ( I ) | E73: 1 | F73: 1 | G73: 0 | H73: =E73*F73*G73 -> 0 | K73: 0 | L73: =H73 -> 0 | U73: 0 | V73: 0 | W73: =(H73-U73)-V73 -> 0 | X73: 1 | Y73: =W73-(W73*X73) -> 0 | Z73: =U73*10% -> 0 | AA73: =(W73+Z73)-Y73 -> 0 | AD73: =B73 -> 4.17 | AE73: =T73 -> 0 | AF73: =U73 -> 0 | AG73: 0 | AH73: =H73-AF73 -> 0 | AI73: =AF73*10% -> 0 | AJ73: =AN73+AI73 -> 0 | AK73: NÃO | AL73: NÃO | AM73: 0 | AN73: =(AH73-(AH73*AM73)) -> 0 | AP73: 0
B74: 4.18 | C74: Mobiliário hotel Cadeiras, pranchões, toalhas sob responsabilidade do hotel. Espaços plenária, salas e outras demandas. Valor sujeito a alteração sem aviso prévio. Sujeito à disponibilidade em estoque de modelo e cores. Prazo para aprovação: Sem realização de pré reserva sem a realização do pagamento de sinal ou assinatura do contrato. | D74: ( I ) | E74: 1 | F74: 1 | G74: 0 | H74: =E74*F74*G74 -> 0 | K74: 0 | L74: =H74 -> 0 | U74: 0 | V74: 0 | W74: =(H74-U74)-V74 -> 0 | X74: 1 | Y74: =W74-(W74*X74) -> 0 | Z74: =U74*10% -> 0 | AA74: =(W74+Z74)-Y74 -> 0 | AD74: =B74 -> 4.18 | AE74: =T74 -> 0 | AF74: =U74 -> 0 | AG74: 0 | AH74: =H74-AF74 -> 0 | AI74: =AF74*10% -> 0 | AJ74: =AN74+AI74 -> 0 | AK74: NÃO | AL74: NÃO | AM74: 0 | AN74: =(AH74-(AH74*AM74)) -> 0 | AP74: 0
B75: 4.19 | C75: Paisagismo Valor sujeito a alteração sem aviso prévio. Sujeito à disponibilidade em estoque de modelo e cores. 3D apresentado com referências podendo sofrer alteração. Prazo para aprovação: | D75: ( I ) | E75: 1 | F75: 1 | G75: 0 | H75: =E75*F75*G75 -> 0 | K75: 0 | L75: =H75 -> 0 | U75: 0 | V75: 0 | W75: =(H75-U75)-V75 -> 0 | X75: 1 | Y75: =W75-(W75*X75) -> 0 | Z75: =U75*10% -> 0 | AA75: =(W75+Z75)-Y75 -> 0 | AD75: =B75 -> 4.19 | AE75: =T75 -> 0 | AF75: =U75 -> 0 | AG75: 0 | AH75: =H75-AF75 -> 0 | AI75: =AF75*10% -> 0 | AJ75: =AN75+AI75 -> 0 | AK75: NÃO | AL75: NÃO | AM75: 0 | AN75: =(AH75-(AH75*AM75)) -> 0 | AP75: 0
B76: 4.20 | C76: Decoração Floral Valor sujeito a alteração sem aviso prévio. Sujeito à disponibilidade em estoque de modelo e cores. 3D apresentado com referências podendo sofrer alteração. Prazo para aprovação: | D76: ( I ) | E76: 1 | F76: 1 | G76: 0 | H76: =E76*F76*G76 -> 0 | K76: 0 | L76: =H76 -> 0 | U76: 0 | V76: 0 | W76: =(H76-U76)-V76 -> 0 | X76: 1 | Y76: =W76-(W76*X76) -> 0 | Z76: =U76*10% -> 0 | AA76: =(W76+Z76)-Y76 -> 0 | AD76: =B76 -> 4.20 | AE76: =T76 -> 0 | AF76: =U76 -> 0 | AG76: 0 | AH76: =H76-AF76 -> 0 | AI76: =AF76*10% -> 0 | AJ76: =AN76+AI76 -> 0 | AK76: NÃO | AL76: NÃO | AM76: 0 | AN76: =(AH76-(AH76*AM76)) -> 0 | AP76: 0
B77: 4.21 | C77: Arranjo de mesa Valor sujeito a alteração sem aviso prévio. Sujeito à disponibilidade em estoque de modelo e cores. 3D apresentado com referências podendo sofrer alteração. Prazo para aprovação: | D77: ( I ) | E77: 1 | F77: 1 | G77: 0 | H77: =E77*F77*G77 -> 0 | K77: 0 | L77: =H77 -> 0 | U77: 0 | V77: 0 | W77: =(H77-U77)-V77 -> 0 | X77: 1 | Y77: =W77-(W77*X77) -> 0 | Z77: =U77*10% -> 0 | AA77: =(W77+Z77)-Y77 -> 0 | AD77: =B77 -> 4.21 | AE77: =T77 -> 0 | AF77: =U77 -> 0 | AG77: 0 | AH77: =H77-AF77 -> 0 | AI77: =AF77*10% -> 0 | AJ77: =AN77+AI77 -> 0 | AK77: NÃO | AL77: NÃO | AM77: 0 | AN77: =(AH77-(AH77*AM77)) -> 0 | AP77: 0
B78: 4.22 | C78: Decorador Período de contratação: Valor sujeito a alteração sem aviso prévio. Prazo para aprovação: | D78: ( I ) | E78: 1 | F78: 1 | G78: 0 | H78: =E78*F78*G78 -> 0 | K78: 0 | L78: =H78 -> 0 | U78: 0 | V78: 0 | W78: =(H78-U78)-V78 -> 0 | X78: 1 | Y78: =W78-(W78*X78) -> 0 | Z78: =U78*10% -> 0 | AA78: =(W78+Z78)-Y78 -> 0 | AD78: =B78 -> 4.22 | AE78: =T78 -> 0 | AF78: =U78 -> 0 | AG78: 0 | AH78: =H78-AF78 -> 0 | AI78: =AF78*10% -> 0 | AJ78: =AN78+AI78 -> 0 | AK78: NÃO | AL78: NÃO | AM78: 0 | AN78: =(AH78-(AH78*AM78)) -> 0 | AP78: 0
B79: 4.23 | C79: Aderecista Período de contratação: Valor sujeito a alteração sem aviso prévio. Prazo para aprovação: | D79: ( I ) | E79: 1 | F79: 1 | G79: 0 | H79: =E79*F79*G79 -> 0 | K79: 0 | L79: =H79 -> 0 | U79: 0 | V79: 0 | W79: =(H79-U79)-V79 -> 0 | X79: 1 | Y79: =W79-(W79*X79) -> 0 | Z79: =U79*10% -> 0 | AA79: =(W79+Z79)-Y79 -> 0 | AD79: =B79 -> 4.23 | AE79: =T79 -> 0 | AF79: =U79 -> 0 | AG79: 0 | AH79: =H79-AF79 -> 0 | AI79: =AF79*10% -> 0 | AJ79: =AN79+AI79 -> 0 | AK79: NÃO | AL79: NÃO | AM79: 0 | AN79: =(AH79-(AH79*AM79)) -> 0 | AP79: 0
B80: 4.24 | C80: Louças Período de locação: Valor sujeito a alteração sem aviso prévio e conforme alteração do escopo. Modelos e cores sujeitos à disponibiidade em estoque. Prazo para aprovação: Sem realização de pré reserva sem a realização do pagamento de sinal ou assinatura do contrato. | D80: ( I ) | E80: 1 | F80: 1 | G80: 0 | H80: =E80*F80*G80 -> 0 | K80: 0 | L80: =H80 -> 0 | U80: 0 | V80: 0 | W80: =(H80-U80)-V80 -> 0 | X80: 1 | Y80: =W80-(W80*X80) -> 0 | Z80: =U80*10% -> 0 | AA80: =(W80+Z80)-Y80 -> 0 | AD80: =B80 -> 4.24 | AE80: =T80 -> 0 | AF80: =U80 -> 0 | AG80: 0 | AH80: =H80-AF80 -> 0 | AI80: =AF80*10% -> 0 | AJ80: =AN80+AI80 -> 0 | AK80: NÃO | AL80: NÃO | AM80: 0 | AN80: =(AH80-(AH80*AM80)) -> 0 | AP80: 0
B81: 4.25 | C81: Acessórios para mesa (guardanapos em tecido, sousplat) Período de locação: Valor sujeito a alteração sem aviso prévio e conforme alteração do escopo. Modelos e cores sujeitos à disponibiidade em estoque. Prazo para aprovação: Sem realização de pré reserva sem a realização do pagamento de sinal ou assinatura do contrato. | D81: ( I ) | E81: 1 | F81: 1 | G81: 0 | H81: =E81*F81*G81 -> 0 | K81: 0 | L81: =H81 -> 0 | U81: 0 | V81: 0 | W81: =(H81-U81)-V81 -> 0 | X81: 1 | Y81: =W81-(W81*X81) -> 0 | Z81: =U81*10% -> 0 | AA81: =(W81+Z81)-Y81 -> 0 | AD81: =B81 -> 4.25 | AE81: =T81 -> 0 | AF81: =U81 -> 0 | AG81: 0 | AH81: =H81-AF81 -> 0 | AI81: =AF81*10% -> 0 | AJ81: =AN81+AI81 -> 0 | AK81: NÃO | AL81: NÃO | AM81: 0 | AN81: =(AH81-(AH81*AM81)) -> 0 | AP81: 0
B82: 5 | C82: TÉCNICA | I82: =SUM(H83:H99) -> 0 | K82: À VISTA ANTECIPADO | L82: =L$15 -> 30 DIAS | P82: ORÇAMENTO 1 | Q82: ORÇAMENTO 2 | R82: ORÇAMENTO 3 | T82: FORNECEDOR | U82: CUSTO REAL | V82: TAXA BANCÁRIA | W82: SOBRA | X82: DEDUÇÃO DE IMPOSTO (FORNECEDOR) | Z82: PDI | AA82: TOTAL (SOBRA + PDI) | AC82: STATUS PRODUÇÃO | AD82: LINHA OC | AE82: FORNECEDOR | AF82: CUSTO REAL | AG82: TAXA BANCÁRIA | AH82: SOBRA | AI82: PDI | AJ82: TOTAL (SOBRA + PDI) | AK82: FECHAR ITEM | AL82: PRECISA DE NOTA DE COBERTURA? | AM82: DEDUÇÃO DE IMPOSTO (FORNECEDOR) | AO82: CÓDIGO FORNECEDOR - PUBLI | AP82: VENCIMENTO | AQ82: AUTORIZAÇÃO DE PRODUÇÃO ENVIADO
B83: 5.1 | C83: Equipamentos - sonorização Valor sujeito a alteração sem aviso prévio e caso haja alteração do escopo. Valor e equipamentos sujeitos à disponibilidade em estoque. Prazo para aprovação: | D83: ( I ) | E83: 1 | F83: 1 | G83: 0 | H83: =E83*F83*G83 -> 0 | K83: 0 | L83: =H83 -> 0 | U83: 0 | V83: 0 | W83: =(H83-U83)-V83 -> 0 | X83: 1 | Y83: =W83-(W83*X83) -> 0 | Z83: =U83*10% -> 0 | AA83: =(W83+Z83)-Y83 -> 0 | AD83: =B83 -> 5.1 | AE83: =T83 -> 0 | AF83: =U83 -> 0 | AG83: 0 | AH83: =H83-AF83 -> 0 | AI83: =AF83*10% -> 0 | AJ83: =AN83+AI83 -> 0 | AK83: NÃO | AL83: NÃO | AM83: 0 | AN83: =(AH83-(AH83*AM83)) -> 0 | AP83: 0
B84: 5.2 | C84: Equipamentos - iluminação cenográfica Valor sujeito a alteração sem aviso prévio e caso haja alteração do escopo. Valor e equipamentos sujeitos à disponibilidade em estoque. Prazo para aprovação: | D84: ( I ) | E84: 1 | F84: 1 | G84: 0 | H84: =E84*F84*G84 -> 0 | K84: 0 | L84: =H84 -> 0 | U84: 0 | V84: 0 | W84: =(H84-U84)-V84 -> 0 | X84: 1 | Y84: =W84-(W84*X84) -> 0 | Z84: =U84*10% -> 0 | AA84: =(W84+Z84)-Y84 -> 0 | AD84: =B84 -> 5.2 | AE84: =T84 -> 0 | AF84: =U84 -> 0 | AG84: 0 | AH84: =H84-AF84 -> 0 | AI84: =AF84*10% -> 0 | AJ84: =AN84+AI84 -> 0 | AK84: NÃO | AL84: NÃO | AM84: 0 | AN84: =(AH84-(AH84*AM84)) -> 0 | AP84: 0
B85: 5.3 | C85: Iluminação Especial Valor sujeito a alteração sem aviso prévio e caso haja alteração do escopo. Valor e equipamentos sujeitos à disponibilidade em estoque. Prazo para aprovação: | D85: ( I ) | E85: 1 | F85: 1 | G85: 0 | H85: =E85*F85*G85 -> 0 | K85: 0 | L85: =H85 -> 0 | U85: 0 | V85: 0 | W85: =(H85-U85)-V85 -> 0 | X85: 1 | Y85: =W85-(W85*X85) -> 0 | Z85: =U85*10% -> 0 | AA85: =(W85+Z85)-Y85 -> 0 | AD85: =B85 -> 5.3 | AE85: =T85 -> 0 | AF85: =U85 -> 0 | AG85: 0 | AH85: =H85-AF85 -> 0 | AI85: =AF85*10% -> 0 | AJ85: =AN85+AI85 -> 0 | AK85: NÃO | AL85: NÃO | AM85: 0 | AN85: =(AH85-(AH85*AM85)) -> 0 | AP85: 0
B86: 5.4 | C86: Equipamentos - led / gerenciamento Valor sujeito a alteração sem aviso prévio e caso haja alteração do escopo. Valor e equipamentos sujeitos à disponibilidade em estoque. Prazo para aprovação: | D86: ( I ) | E86: 1 | F86: 1 | G86: 0 | H86: =E86*F86*G86 -> 0 | K86: 0 | L86: =H86 -> 0 | U86: 0 | V86: 0 | W86: =(H86-U86)-V86 -> 0 | X86: 1 | Y86: =W86-(W86*X86) -> 0 | Z86: =U86*10% -> 0 | AA86: =(W86+Z86)-Y86 -> 0 | AD86: =B86 -> 5.4 | AE86: =T86 -> 0 | AF86: =U86 -> 0 | AG86: 0 | AH86: =H86-AF86 -> 0 | AI86: =AF86*10% -> 0 | AJ86: =AN86+AI86 -> 0 | AK86: NÃO | AL86: NÃO | AM86: 0 | AN86: =(AH86-(AH86*AM86)) -> 0 | AP86: 0
B87: 5.5 | C87: Projeção Mapeada Valor sujeito a alteração sem aviso prévio e caso haja alteração do escopo. Valor e equipamentos sujeitos à disponibilidade em estoque. Prazo para aprovação: | D87: ( I ) | E87: 1 | F87: 1 | G87: 0 | H87: =E87*F87*G87 -> 0 | K87: 0 | L87: =H87 -> 0 | U87: 0 | V87: 0 | W87: =(H87-U87)-V87 -> 0 | X87: 1 | Y87: =W87-(W87*X87) -> 0 | Z87: =U87*10% -> 0 | AA87: =(W87+Z87)-Y87 -> 0 | AD87: =B87 -> 5.5 | AE87: =T87 -> 0 | AF87: =U87 -> 0 | AG87: 0 | AH87: =H87-AF87 -> 0 | AI87: =AF87*10% -> 0 | AJ87: =AN87+AI87 -> 0 | AK87: NÃO | AL87: NÃO | AM87: 0 | AN87: =(AH87-(AH87*AM87)) -> 0 | AP87: 0
B88: 5.6 | C88: Projeção (projetor) Valor sujeito a alteração sem aviso prévio e caso haja alteração do escopo. Valor e equipamentos sujeitos à disponibilidade em estoque. Prazo para aprovação: | D88: ( I ) | E88: 1 | F88: 1 | G88: 0 | H88: =E88*F88*G88 -> 0 | K88: 0 | L88: =H88 -> 0 | U88: 0 | V88: 0 | W88: =(H88-U88)-V88 -> 0 | X88: 1 | Y88: =W88-(W88*X88) -> 0 | Z88: =U88*10% -> 0 | AA88: =(W88+Z88)-Y88 -> 0 | AD88: =B88 -> 5.6 | AE88: =T88 -> 0 | AF88: =U88 -> 0 | AG88: 0 | AH88: =H88-AF88 -> 0 | AI88: =AF88*10% -> 0 | AJ88: =AN88+AI88 -> 0 | AK88: NÃO | AL88: NÃO | AM88: 0 | AN88: =(AH88-(AH88*AM88)) -> 0 | AP88: 0
B89: 5.7 | C89: Tela de projeção Valor sujeito a alteração sem aviso prévio e caso haja alteração do escopo. Valor e equipamentos sujeitos à disponibilidade em estoque. Prazo para aprovação: | D89: ( I ) | E89: 1 | F89: 1 | G89: 0 | H89: =E89*F89*G89 -> 0 | K89: 0 | L89: =H89 -> 0 | U89: 0 | V89: 0 | W89: =(H89-U89)-V89 -> 0 | X89: 1 | Y89: =W89-(W89*X89) -> 0 | Z89: =U89*10% -> 0 | AA89: =(W89+Z89)-Y89 -> 0 | AD89: =B89 -> 5.7 | AE89: =T89 -> 0 | AF89: =U89 -> 0 | AG89: 0 | AH89: =H89-AF89 -> 0 | AI89: =AF89*10% -> 0 | AJ89: =AN89+AI89 -> 0 | AK89: NÃO | AL89: NÃO | AM89: 0 | AN89: =(AH89-(AH89*AM89)) -> 0 | AP89: 0
B90: 5.8 | C90: Dog house (estrutura + tela) Valor sujeito a alteração sem aviso prévio e caso haja alteração do escopo. Valor e equipamentos sujeitos à disponibilidade em estoque. Prazo para aprovação: | D90: ( I ) | E90: 1 | F90: 1 | G90: 0 | H90: =E90*F90*G90 -> 0 | K90: 0 | L90: =H90 -> 0 | U90: 0 | V90: 0 | W90: =(H90-U90)-V90 -> 0 | X90: 1 | Y90: =W90-(W90*X90) -> 0 | Z90: =U90*10% -> 0 | AA90: =(W90+Z90)-Y90 -> 0 | AD90: =B90 -> 5.8 | AE90: =T90 -> 0 | AF90: =U90 -> 0 | AG90: 0 | AH90: =H90-AF90 -> 0 | AI90: =AF90*10% -> 0 | AJ90: =AN90+AI90 -> 0 | AK90: NÃO | AL90: NÃO | AM90: 0 | AN90: =(AH90-(AH90*AM90)) -> 0 | AP90: 0
B91: 5.9 | C91: Tela de retorno Valor sujeito a alteração sem aviso prévio e caso haja alteração do escopo. Valor e equipamentos sujeitos à disponibilidade em estoque. Prazo para aprovação: | D91: ( I ) | E91: 1 | F91: 1 | G91: 0 | H91: =E91*F91*G91 -> 0 | K91: 0 | L91: =H91 -> 0 | U91: 0 | V91: 0 | W91: =(H91-U91)-V91 -> 0 | X91: 1 | Y91: =W91-(W91*X91) -> 0 | Z91: =U91*10% -> 0 | AA91: =(W91+Z91)-Y91 -> 0 | AD91: =B91 -> 5.9 | AE91: =T91 -> 0 | AF91: =U91 -> 0 | AG91: 0 | AH91: =H91-AF91 -> 0 | AI91: =AF91*10% -> 0 | AJ91: =AN91+AI91 -> 0 | AK91: NÃO | AL91: NÃO | AM91: 0 | AN91: =(AH91-(AH91*AM91)) -> 0 | AP91: 0
B92: 5.10 | C92: Gobos personalizado Valor sujeito a alteração sem aviso prévio e caso haja alteração do escopo. Valor e equipamentos sujeitos à disponibilidade em estoque. Prazo para aprovação: | D92: ( I ) | E92: 1 | F92: 1 | G92: 0 | H92: =E92*F92*G92 -> 0 | K92: 0 | L92: =H92 -> 0 | U92: 0 | V92: 0 | W92: =(H92-U92)-V92 -> 0 | X92: 1 | Y92: =W92-(W92*X92) -> 0 | Z92: =U92*10% -> 0 | AA92: =(W92+Z92)-Y92 -> 0 | AD92: =B92 -> 5.10 | AE92: =T92 -> 0 | AF92: =U92 -> 0 | AG92: 0 | AH92: =H92-AF92 -> 0 | AI92: =AF92*10% -> 0 | AJ92: =AN92+AI92 -> 0 | AK92: NÃO | AL92: NÃO | AM92: 0 | AN92: =(AH92-(AH92*AM92)) -> 0 | AP92: 0
B93: 5.11 | C93: Tvs (com ou sem pedestal) Valor sujeito a alteração sem aviso prévio e caso haja alteração do escopo. Valor e equipamentos sujeitos à disponibilidade em estoque. Prazo para aprovação: | D93: ( I ) | E93: 1 | F93: 1 | G93: 0 | H93: =E93*F93*G93 -> 0 | K93: 0 | L93: =H93 -> 0 | U93: 0 | V93: 0 | W93: =(H93-U93)-V93 -> 0 | X93: 1 | Y93: =W93-(W93*X93) -> 0 | Z93: =U93*10% -> 0 | AA93: =(W93+Z93)-Y93 -> 0 | AD93: =B93 -> 5.11 | AE93: =T93 -> 0 | AF93: =U93 -> 0 | AG93: 0 | AH93: =H93-AF93 -> 0 | AI93: =AF93*10% -> 0 | AJ93: =AN93+AI93 -> 0 | AK93: NÃO | AL93: NÃO | AM93: 0 | AN93: =(AH93-(AH93*AM93)) -> 0 | AP93: 0
B94: 5.12 | C94: Passador de slides com laser point Valor sujeito a alteração sem aviso prévio e caso haja alteração do escopo. Valor e equipamentos sujeitos à disponibilidade em estoque. Prazo para aprovação: | D94: ( I ) | E94: 1 | F94: 1 | G94: 0 | H94: =E94*F94*G94 -> 0 | K94: 0 | L94: =H94 -> 0 | U94: 0 | V94: 0 | W94: =(H94-U94)-V94 -> 0 | X94: 1 | Y94: =W94-(W94*X94) -> 0 | Z94: =U94*10% -> 0 | AA94: =(W94+Z94)-Y94 -> 0 | AD94: =B94 -> 5.12 | AE94: =T94 -> 0 | AF94: =U94 -> 0 | AG94: 0 | AH94: =H94-AF94 -> 0 | AI94: =AF94*10% -> 0 | AJ94: =AN94+AI94 -> 0 | AK94: NÃO | AL94: NÃO | AM94: 0 | AN94: =(AH94-(AH94*AM94)) -> 0 | AP94: 0
... B99: 5.17 | C99: Sonoplasta 01 profissional x XX diária de ensaio + XX diárias de evento. Custo contemplando: Sujeito à disponibilidade para o período. Prazo para aprovação: | D99: ( I ) | E99: 1 | F99: 1 | G99: 0 | H99: =E99*F99*G99 -> 0 | K99: 0 | L99: =H99 -> 0 | U99: 0 | V99: 0 | W99: =(H99-U99)-V99 -> 0 | X99: 1 | Y99: =W99-(W99*X99) -> 0 | Z99: =U99*10% -> 0 | AA99: =(W99+Z99)-Y99 -> 0 | AD99: =B99 -> 5.17 | AE99: =T99 -> 0 | AF99: =U99 -> 0 | AG99: 0 | AH99: =H99-AF99 -> 0 | AI99: =AF99*10% -> 0 | AJ99: =AN99+AI99 -> 0 | AK99: NÃO | AL99: NÃO | AM99: 0 | AN99: =(AH99-(AH99*AM99)) -> 0 | AP99: 0
B100: 6 | C100: INFRAESTRUTURA | I100: =SUM(H101:H148) -> 0 | K100: À VISTA ANTECIPADO | L100: =L$15 -> 30 DIAS | P100: ORÇAMENTO 1 | Q100: ORÇAMENTO 2 | R100: ORÇAMENTO 3 | T100: FORNECEDOR | U100: CUSTO REAL | V100: TAXA BANCÁRIA | W100: SOBRA | X100: DEDUÇÃO DE IMPOSTO (FORNECEDOR) | Z100: PDI | AA100: TOTAL (SOBRA + PDI) | AC100: STATUS PRODUÇÃO | AD100: LINHA OC | AE100: FORNECEDOR | AF100: CUSTO REAL | AG100: TAXA BANCÁRIA | AH100: SOBRA | AI100: PDI | AJ100: TOTAL (SOBRA + PDI) | AK100: FECHAR ITEM | AL100: PRECISA DE NOTA DE COBERTURA? | AM100: DEDUÇÃO DE IMPOSTO (FORNECEDOR) | AO100: CÓDIGO FORNECEDOR - PUBLI | AP100: VENCIMENTO | AQ100: AUTORIZAÇÃO DE PRODUÇÃO ENVIADO
B101: 6.1 | C101: Grupo de Geradores - (Montagem + ensaio / Evento ) Valor sujeito a alteração sem aviso prévio e caso haja alteração do escopo. Valor e equipamentos sujeitos à disponibilidade em estoque. Prazo para aprovação: | D101: ( I ) | E101: 1 | F101: 1 | G101: 0 | H101: =E101*F101*G101 -> 0 | K101: 0 | L101: =H101 -> 0 | U101: 0 | V101: 0 | W101: =(H101-U101)-V101 -> 0 | X101: 1 | Y101: =W101-(W101*X101) -> 0 | Z101: =U101*10% -> 0 | AA101: =(W101+Z101)-Y101 -> 0 | AD101: =B101 -> 6.1 | AE101: =T101 -> 0 | AF101: =U101 -> 0 | AG101: 0 | AH101: =H101-AF101 -> 0 | AI101: =AF101*10% -> 0 | AJ101: =AN101+AI101 -> 0 | AK101: NÃO | AL101: NÃO | AM101: 0 | AN101: =(AH101-(AH101*AM101)) -> 0 | AP101: 0
B102: 6.2 | C102: Passa cabo Valor sujeito a alteração sem aviso prévio e caso haja alteração do escopo. Valor e equipamentos sujeitos à disponibilidade em estoque. Prazo para aprovação: | D102: ( I ) | E102: 1 | F102: 1 | G102: 0 | H102: =E102*F102*G102 -> 0 | K102: 0 | L102: =H102 -> 0 | U102: 0 | V102: 0 | W102: =(H102-U102)-V102 -> 0 | X102: 1 | Y102: =W102-(W102*X102) -> 0 | Z102: =U102*10% -> 0 | AA102: =(W102+Z102)-Y102 -> 0 | AD102: =B102 -> 6.2 | AE102: =T102 -> 0 | AF102: =U102 -> 0 | AG102: 0 | AH102: =H102-AF102 -> 0 | AI102: =AF102*10% -> 0 | AJ102: =AN102+AI102 -> 0 | AK102: NÃO | AL102: NÃO | AM102: 0 | AN102: =(AH102-(AH102*AM102)) -> 0 | AP102: 0
B103: 6.3 | C103: Eletricista 01 profissional x XX diária de montagem + XX diárias de evento. Custo contemplando: Sujeito à disponibilidade para o período. Prazo para aprovação: | D103: ( I ) | E103: 1 | F103: 1 | G103: 0 | H103: =E103*F103*G103 -> 0 | K103: 0 | L103: =H103 -> 0 | U103: 0 | V103: 0 | W103: =(H103-U103)-V103 -> 0 | X103: 1 | Y103: =W103-(W103*X103) -> 0 | Z103: =U103*10% -> 0 | AA103: =(W103+Z103)-Y103 -> 0 | AD103: =B103 -> 6.3 | AE103: =T103 -> 0 | AF103: =U103 -> 0 | AG103: 0 | AH103: =H103-AF103 -> 0 | AI103: =AF103*10% -> 0 | AJ103: =AN103+AI103 -> 0 | AK103: NÃO | AL103: NÃO | AM103: 0 | AN103: =(AH103-(AH103*AM103)) -> 0 | AP103: 0
B104: 6.4 | C104: Arquibancada Valor sujeito a alteração sem aviso prévio e caso haja alteração do escopo. Valor e equipamentos sujeitos à disponibilidade em estoque. Prazo para aprovação: | D104: ( I ) | E104: 1 | F104: 1 | G104: 0 | H104: =E104*F104*G104 -> 0 | K104: 0 | L104: =H104 -> 0 | U104: 0 | V104: 0 | W104: =(H104-U104)-V104 -> 0 | X104: 1 | Y104: =W104-(W104*X104) -> 0 | Z104: =U104*10% -> 0 | AA104: =(W104+Z104)-Y104 -> 0 | AD104: =B104 -> 6.4 | AE104: =T104 -> 0 | AF104: =U104 -> 0 | AG104: 0 | AH104: =H104-AF104 -> 0 | AI104: =AF104*10% -> 0 | AJ104: =AN104+AI104 -> 0 | AK104: NÃO | AL104: NÃO | AM104: 0 | AN104: =(AH104-(AH104*AM104)) -> 0 | AP104: 0
B105: 6.5 | C105: Palco Valor sujeito a alteração sem aviso prévio e caso haja alteração do escopo. Valor e equipamentos sujeitos à disponibilidade em estoque. Prazo para aprovação: | D105: ( I ) | E105: 1 | F105: 1 | G105: 0 | H105: =E105*F105*G105 -> 0 | K105: 0 | L105: =H105 -> 0 | U105: 0 | V105: 0 | W105: =(H105-U105)-V105 -> 0 | X105: 1 | Y105: =W105-(W105*X105) -> 0 | Z105: =U105*10% -> 0 | AA105: =(W105+Z105)-Y105 -> 0 | AD105: =B105 -> 6.5 | AE105: =T105 -> 0 | AF105: =U105 -> 0 | AG105: 0 | AH105: =H105-AF105 -> 0 | AI105: =AF105*10% -> 0 | AJ105: =AN105+AI105 -> 0 | AK105: NÃO | AL105: NÃO | AM105: 0 | AN105: =(AH105-(AH105*AM105)) -> 0 | AP105: 0
B106: 6.6 | C106: Estrutura metálica para led Valor sujeito a alteração sem aviso prévio e caso haja alteração do escopo. Valor e equipamentos sujeitos à disponibilidade em estoque. Prazo para aprovação: | D106: ( I ) | E106: 1 | F106: 1 | G106: 0 | H106: =E106*F106*G106 -> 0 | K106: 0 | L106: =H106 -> 0 | U106: 0 | V106: 0 | W106: =(H106-U106)-V106 -> 0 | X106: 1 | Y106: =W106-(W106*X106) -> 0 | Z106: =U106*10% -> 0 | AA106: =(W106+Z106)-Y106 -> 0 | AD106: =B106 -> 6.6 | AE106: =T106 -> 0 | AF106: =U106 -> 0 | AG106: 0 | AH106: =H106-AF106 -> 0 | AI106: =AF106*10% -> 0 | AJ106: =AN106+AI106 -> 0 | AK106: NÃO | AL106: NÃO | AM106: 0 | AN106: =(AH106-(AH106*AM106)) -> 0 | AP106: 0
B107: 6.7 | C107: Praticáveis Valor sujeito a alteração sem aviso prévio e caso haja alteração do escopo. Valor e equipamentos sujeitos à disponibilidade em estoque. Prazo para aprovação: | D107: ( I ) | E107: 1 | F107: 1 | G107: 0 | H107: =E107*F107*G107 -> 0 | K107: 0 | L107: =H107 -> 0 | U107: 0 | V107: 0 | W107: =(H107-U107)-V107 -> 0 | X107: 1 | Y107: =W107-(W107*X107) -> 0 | Z107: =U107*10% -> 0 | AA107: =(W107+Z107)-Y107 -> 0 | AD107: =B107 -> 6.7 | AE107: =T107 -> 0 | AF107: =U107 -> 0 | AG107: 0 | AH107: =H107-AF107 -> 0 | AI107: =AF107*10% -> 0 | AJ107: =AN107+AI107 -> 0 | AK107: NÃO | AL107: NÃO | AM107: 0 | AN107: =(AH107-(AH107*AM107)) -> 0 | AP107: 0
...

Sheet GRADE
C8: MONTAGEM | G8: EVENTO | K8: DESMONTAGEM
C9: SEG | D9: TER | E9: QUA | F9: QUI | G9: SEX | H9: SAB | I9: DOM | J9: SEG | K9: TER | L9: QUA | M9: QUI | N9: TOTAL
B10: LIMPEZA | C10: 45505 | D10: 45506 | E10: 45507 | F10: 45508 | G10: 45509 | H10: 45510 | I10: 45511 | J10: 45512 | K10: 45513 | L10: 45514 | M10: 45515
B11: 08h00 as 20h00 | N11: =SUM(C11:M11) -> 0
B12: 10h00 as 22h00 | N12: =SUM(C12:M12) -> 0
B13: 13h00 as 01h00 | N13: =SUM(C13:M13) -> 0
B14: 20h00 as 08h00 | N14: =SUM(C14:M14) -> 0
N15: =SUM(N11:N14) -> 0
C19: MONTAGEM | G19: EVENTO | K19: DESMONTAGEM
C20: SEG | D20: TER | E20: QUA | F20: QUI | G20: SEX | H20: SAB | I20: DOM | J20: SEG | K20: TER | L20: QUA | M20: QUI | N20: TOTAL
B21: SEGURANÇA | C21: 45505 | D21: 45506 | E21: 45507 | F21: 45508 | G21: 45509 | H21: 45510 | I21: 45511 | J21: 45512 | K21: 45513 | L21: 45514 | M21: 45515
B22: 08h00 as 20h00 | N22: =SUM(C22:M22) -> 0
B23: 10h00 as 22h00 | N23: =SUM(C23:M23) -> 0
B24: 13h00 as 01h00 | N24: =SUM(C24:M24) -> 0
B25: 20h00 as 08h00 | N25: =SUM(C25:M25) -> 0
N26: =SUM(N22:N25) -> 0
C30: MONTAGEM | G30: EVENTO | K30: DESMONTAGEM
C31: SEG | D31: TER | E31: QUA | F31: QUI | G31: SEX | H31: SAB | I31: DOM | J31: SEG | K31: TER | L31: QUA | M31: QUI | N31: TOTAL
B32: CARREGADORES | C32: 45505 | D32: 45506 | E32: 45507 | F32: 45508 | G32: 45509 | H32: 45510 | I32: 45511 | J32: 45512 | K32: 45513 | L32: 45514 | M32: 45515
B33: 08h00 as 20h00 | N33: =SUM(C33:M33) -> 0
B34: 10h00 as 22h00 | N34: =SUM(C34:M34) -> 0
B35: 13h00 as 01h00 | N35: =SUM(C35:M35) -> 0
B36: 20h00 as 08h00 | N36: =SUM(C36:M36) -> 0
N37: =SUM(N33:N36) -> 0
C41: MONTAGEM | G41: EVENTO | K41: DESMONTAGEM
C42: SEG | D42: TER | E42: QUA | F42: QUI | G42: SEX | H42: SAB | I42: DOM | J42: SEG | K42: TER | L42: QUA | M42: QUI | N42: TOTAL
B43: BRIGADISTAS | C43: 45505 | D43: 45506 | E43: 45507 | F43: 45508 | G43: 45509 | H43: 45510 | I43: 45511 | J43: 45512 | K43: 45513 | L43: 45514 | M43: 45515
B44: 08h00 as 20h00 | N44: =SUM(C44:M44) -> 0
B45: 10h00 as 22h00 | N45: =SUM(C45:M45) -> 0
B46: 13h00 as 01h00 | N46: =SUM(C46:M46) -> 0
B47: 20h00 as 08h00 | N47: =SUM(C47:M47) -> 0
N48: =SUM(N44:N47) -> 0
C51: MONTAGEM | G51: EVENTO | K51: DESMONTAGEM
C52: SEG | D52: TER | E52: QUA | F52: QUI | G52: SEX | H52: SAB | I52: DOM | J52: SEG | K52: TER | L52: QUA | M52: QUI | N52: TOTAL
B53: AMBULÂNCIA SIMPLES | C53: 45505 | D53: 45506 | E53: 45507 | F53: 45508 | G53: 45509 | H53: 45510 | I53: 45511 | J53: 45512 | K53: 45513 | L53: 45514 | M53: 45515
B54: 08h00 as 20h00 | N54: =SUM(C54:M54) -> 0
B55: 10h00 as 22h00 | N55: =SUM(C55:M55) -> 0
B56: 13h00 as 01h00 | N56: =SUM(C56:M56) -> 0
B57: 20h00 as 08h00 | N57: =SUM(C57:M57) -> 0
N58: =SUM(N54:N57) -> 0
C62: MONTAGEM | G62: EVENTO | K62: DESMONTAGEM
C63: SEG | D63: TER | E63: QUA | F63: QUI | G63: SEX | H63: SAB | I63: DOM | J63: SEG | K63: TER | L63: QUA | M63: QUI | N63: TOTAL
B64: AMBULÂNCIA UTI | C64: 45505 | D64: 45506 | E64: 45507 | F64: 45508 | G64: 45509 | H64: 45510 | I64: 45511 | J64: 45512 | K64: 45513 | L64: 45514 | M64: 45515
B65: 08h00 as 20h00 | N65: =SUM(C65:M65) -> 0
B66: 10h00 as 22h00 | N66: =SUM(C66:M66) -> 0
B67: 13h00 as 01h00 | N67: =SUM(C67:M67) -> 0
B68: 20h00 as 08h00 | N68: =SUM(C68:M68) -> 0
N69: =SUM(N65:N68) -> 0
B73: *Incluir a quantidade de refeição / pax / dia | C73: MONTAGEM | G73: EVENTO | K73: DESMONTAGEM
C74: SEG | D74: TER | E74: QUA | F74: QUI | G74: SEX | H74: SAB | I74: DOM | J74: SEG | K74: TER | L74: QUA | M74: QUI | N74: TOTAL
B75: ALIMENTAÇÃO | C75: 45505 | D75: 45506 | E75: 45507 | F75: 45508 | G75: 45509 | H75: 45510 | I75: 45511 | J75: 45512 | K75: 45513 | L75: 45514 | M75: 45515
B76: Atendimento | N76: =SUM(C76:M76) -> 0
B77: Diretor de atendimento | N77: =SUM(C77:M77) -> 0
B78: Dirertor de produção | N78: =SUM(C78:M78) -> 0
B79: Head de produção | N79: =SUM(C79:M79) -> 0
B80: Executivo | N80: =SUM(C80:M80) -> 0
B81: Assistente do executivo | N81: =SUM(C81:M81) -> 0
C82: =SUM(C76:C81) -> 0 | D82: =SUM(D76:D81) -> 0 | E82: =SUM(E76:E81) -> 0 | F82: =SUM(F76:F81) -> 0 | G82: =SUM(G76:G81) -> 0 | H82: =SUM(H76:H81) -> 0 | I82: =SUM(I76:I81) -> 0 | J82: =SUM(J76:J81) -> 0 | ... N82: =SUM(N76:N81) -> 0
C87: MONTAGEM | G87: EVENTO | K87: DESMONTAGEM
C88: SEG | D88: TER | E88: QUA | F88: QUI | G88: SEX | H88: SAB | I88: DOM | J88: SEG | K88: TER | L88: QUA | M88: QUI | N88: TOTAL
B89: RÁDIO HT | C89: 45505 | D89: 45506 | E89: 45507 | F89: 45508 | G89: 45509 | H89: 45510 | I89: 45511 | J89: 45512 | K89: 45513 | L89: 45514 | M89: 45515
B90: Atendimento | N90: =SUM(C90:M90) -> 0
B91: Diretor de atendimento | N91: =SUM(C91:M91) -> 0
B92: Dirertor de produção | N92: =SUM(C92:M92) -> 0
B93: Head de produção | N93: =SUM(C93:M93) -> 0
B94: Executivo | N94: =SUM(C94:M94) -> 0
B95: Assistente do executivo | N95: =SUM(C95:M95) -> 0
C96: =SUM(C90:C95) -> 0 | D96: =SUM(D90:D95) -> 0 | E96: =SUM(E90:E95) -> 0 | F96: =SUM(F90:F95) -> 0 | G96: =SUM(G90:G95) -> 0 | H96: =SUM(H90:H95) -> 0 | I96: =SUM(I90:I95) -> 0 | J96: =SUM(J90:J95) -> 0 | ... N96: =SUM(N90:N95) -> 0
C101: MONTAGEM | G101: EVENTO | K101: DESMONTAGEM
C102: SEG | D102: TER | E102: QUA | F102: QUI | G102: SEX | H102: SAB | I102: DOM | J102: SEG | K102: TER | L102: QUA | M102: QUI | N102: TOTAL
B103: HOSPEDAGEM | C103: 45505 | D103: 45506 | E103: 45507 | F103: 45508 | G103: 45509 | H103: 45510 | I103: 45511 | J103: 45512 | K103: 45513 | L103: 45514 | M103: 45515
B104: Atendimento | N104: =SUM(C104:M104) -> 0
B105: Diretor de atendimento | N105: =SUM(C105:M105) -> 0
B106: Dirertor de produção | N106: =SUM(C106:M106) -> 0
B107: Head de produção | N107: =SUM(C107:M107) -> 0
B108: Executivo | N108: =SUM(C108:M108) -> 0
B109: Assistente do executivo | N109: =SUM(C109:M109) -> 0
C110: =SUM(C104:C109) -> 0 | D110: =SUM(D104:D109) -> 0 | E110: =SUM(E104:E109) -> 0 | F110: =SUM(F104:F109) -> 0 | G110: =SUM(G104:G109) -> 0 | H110: =SUM(H104:H109) -> 0 | I110: =SUM(I104:I109) -> 0 | J110: =SUM(J104:J109) -> 0 | ... N110: =SUM(N104:N109) -> 0
C115: MONTAGEM | G115: EVENTO | K115: DESMONTAGEM
C116: SEG | D116: TER | E116: QUA | F116: QUI | G116: SEX | H116: SAB | I116: DOM | J116: SEG | K116: TER | L116: QUA | M116: QUI | N116: TOTAL
B117: PROMOTORAS | C117: 45505 | D117: 45506 | E117: 45507 | F117: 45508 | G117: 45509 | H117: 45510 | I117: 45511 | J117: 45512 | K117: 45513 | L117: 45514 | M117: 45515
B118: 08h00 as 20h00 | N118: =SUM(C118:M118) -> 0
B119: 10h00 as 22h00 | N119: =SUM(C119:M119) -> 0
B120: 13h00 as 01h00 | N120: =SUM(C120:M120) -> 0
B121: 20h00 as 08h00 | N121: =SUM(C121:M121) -> 0
N122: =SUM(N118:N121) -> 0

Sheet CRONOGRAMA
C8: Última atualização em: | D8: =TODAY() -> 46196 | J8: qua | K8: qui | L8: sex | M8: sáb | N8: dom | O8: seg | P8: ter | Q8: qua | R8: qui | S8: sex | T8: sáb | U8: dom | V8: seg | W8: ter | X8: qua | Y8: qui | Z8: sex | AA8: sáb | AB8: dom | AC8: seg | AD8: ter | AE8: qua | AF8: qui | AG8: sex | AH8: sáb | AI8: dom | AJ8: seg | AK8: ter | AL8: qua | AM8: qui | AN8: sex | AO8: sáb | AP8: dom | AQ8: seg | AR8: ter | AS8: qua | AT8: qui | AU8: sex | AV8: sáb | AW8: dom | AX8: seg | AY8: ter | AZ8: qua | BA8: qui | BB8: sex | BC8: sáb | BD8: dom | BE8: seg | BF8: ter | BG8: qua | BH8: qui | BI8: sex | BJ8: sáb | BK8: dom | BL8: seg | BM8: ter | BN8: qua | BO8: qui | BP8: sex | BQ8: sáb | BR8: dom | BS8: seg | BT8: ter | BU8: qua | BV8: qui | BW8: sex | BX8: sáb | BY8: dom | BZ8: seg | CA8: ter | CB8: qua | CC8: qui | CD8: sex | CE8: sáb | CF8: dom | CG8: seg | CH8: ter | CI8: qua | CJ8: qui | CK8: sex | CL8: sáb | CM8: dom | CN8: seg | CO8: ter | CP8: qua | CQ8: qui | CR8: sex | CS8: sáb | CT8: dom | CU8: seg | CV8: ter | CW8: qua | CX8: qui | CY8: sex | CZ8: sáb | DA8: dom | DB8: seg | DC8: ter | DD8: qua | DE8: qui | DF8: sex | DG8: sáb | DH8: dom | DI8: seg | DJ8: ter | DK8: qua | DL8: qui | DM8: sex | DN8: sáb | DO8: dom | DP8: seg | DQ8: ter | DR8: qua | DS8: qui | DT8: sex | DU8: sáb | DV8: dom | DW8: seg | DX8: ter | DY8: qua | DZ8: qui | EA8: sex | EB8: sáb | EC8: dom | ED8: seg | EE8: ter | EF8: qua | EG8: qui | EH8: sex | EI8: sáb | EJ8: dom | EK8: seg | EL8: ter | EM8: qua | EN8: qui | EO8: sex | EP8: sáb | EQ8: dom | ER8: seg | ES8: ter | ET8: qua | EU8: qui | EV8: sex | EW8: sáb | EX8: dom | EY8: seg | EZ8: ter | FA8: qua | FB8: qui | FC8: sex | FD8: sáb | FE8: dom | FF8: seg | FG8: ter | FH8: qua | FI8: qui | FJ8: sex | FK8: sáb | FL8: dom | FM8: seg | FN8: ter | FO8: qua | FP8: qui | FQ8: sex | FR8: sáb | FS8: dom | FT8: seg | FU8: ter | FV8: qua | FW8: qui | FX8: sex | FY8: sáb | FZ8: dom | GA8: seg | GB8: ter | GC8: qua | GD8: qui | GE8: sex | GF8: sáb | GG8: dom | GH8: seg | GI8: ter | GJ8: qua | GK8: qui | GL8: sex | GM8: sáb | GN8: dom | GO8: seg | GP8: ter | GQ8: qua | GR8: qui | GS8: sex | GT8: sáb | GU8: dom | GV8: seg | GW8: ter | GX8: qua | GY8: qui | GZ8: sex | HA8: sáb | HB8: dom | HC8: seg | HD8: ter | HE8: qua | HF8: qui | HG8: sex | HH8: sáb | HI8: dom | HJ8: seg | HK8: ter | HL8: qua | HM8: qui | HN8: sex | HO8: sáb | HP8: dom | HQ8: seg | HR8: ter | HS8: qua | HT8: qui | HU8: sex | HV8: sáb | HW8: dom | HX8: seg | HY8: ter | HZ8: qua | IA8: qui | IB8: sex | IC8: sáb | ID8: dom | IE8: seg | IF8: ter | IG8: qua | IH8: qui | II8: sex | IJ8: sáb | IK8: dom | IL8: seg | IM8: ter | IN8: qua | IO8: qui | IP8: sex | IQ8: sáb | IR8: dom | IS8: seg | IT8: ter | IU8: qua | IV8: qui | IW8: sex | IX8: sáb | IY8: dom | IZ8: seg | JA8: ter | JB8: qua | JC8: qui | JD8: sex | JE8: sáb | JF8: dom | JG8: seg | JH8: ter | JI8: qua | JJ8: qui | JK8: sex | JL8: sáb | JM8: dom | JN8: seg | JO8: ter | JP8: qua | JQ8: qui | JR8: sex | JS8: sáb | JT8: dom | JU8: seg | JV8: ter | JW8: qua | JX8: qui | JY8: sex | JZ8: sáb | KA8: dom | KB8: seg | KC8: ter | KD8: qua | KE8: qui | KF8: sex | KG8: sáb | KH8: dom | KI8: seg | KJ8: ter | KK8: qua | KL8: qui | KM8: sex | KN8: sáb | KO8: dom | KP8: seg | KQ8: ter | KR8: qua | KS8: qui | KT8: sex | KU8: sáb | KV8: dom | KW8: seg | KX8: ter | KY8: qua | KZ8: qui | LA8: sex | LB8: sáb | LC8: dom | LD8: seg | LE8: ter | LF8: qua | LG8: qui | LH8: sex | LI8: sáb | LJ8: dom | LK8: seg | LL8: ter | LM8: qua | LN8: qui | LO8: sex | LP8: sáb | LQ8: dom | LR8: seg | LS8: ter | LT8: qua | LU8: qui | LV8: sex | LW8: sáb | LX8: dom | LY8: seg | LZ8: ter | MA8: qua | MB8: qui | MC8: sex | MD8: sáb | ME8: dom | MF8: seg | MG8: ter | MH8: qua | MI8: qui | MJ8: sex | MK8: sáb | ML8: dom | MM8: seg | MN8: ter | MO8: qua | MP8: qui | MQ8: sex | MR8: sáb | MS8: dom | MT8: seg | MU8: ter | MV8: qua | MW8: qui | MX8: sex | MY8: sáb | MZ8: dom | NA8: seg | NB8: ter | NC8: qua | ND8: qui | NE8: sex | NF8: sáb | NG8: dom | NH8: seg | NI8: ter | NJ8: qua
C9: Item | D9: Início | E9: Término | F9: Dias | G9: Responsável | H9: Status | I9: Observações | J9: 45658 | K9: 45659 | L9: 45660 | M9: 45661 | N9: 45662 | O9: 45663 | P9: 45664 | Q9: 45665 | R9: 45666 | S9: 45667 | T9: 45668 | U9: 45669 | V9: 45670 | W9: 45671 | X9: 45672 | Y9: 45673 | Z9: 45674 | AA9: 45675 | AB9: 45676 | AC9: 45677 | AD9: 45678 | AE9: 45679 | AF9: 45680 | AG9: 45681 | AH9: 45682 | AI9: 45683 | AJ9: 45684 | AK9: 45685 | AL9: 45686 | AM9: 45687 | AN9: 45688 | AO9: 45689 | AP9: 45690 | AQ9: 45691 | AR9: 45692 | AS9: 45693 | AT9: 45694 | AU9: 45695 | AV9: 45696 | AW9: 45697 | AX9: 45698 | AY9: 45699 | AZ9: 45700 | BA9: 45701 | BB9: 45702 | BC9: 45703 | BD9: 45704 | BE9: 45705 | BF9: 45706 | BG9: 45707 | BH9: 45708 | BI9: 45709 | BJ9: 45710 | BK9: 45711 | BL9: 45712 | BM9: 45713 | BN9: 45714 | BO9: 45715 | BP9: 45716 | BQ9: 45717 | BR9: 45718 | BS9: 45719 | BT9: 45720 | BU9: 45721 | BV9: 45722 | BW9: 45723 | BX9: 45724 | BY9: 45725 | BZ9: 45726 | CA9: 45727 | CB9: 45728 | CC9: 45729 | CD9: 45730 | CE9: 45731 | CF9: 45732 | CG9: 45733 | CH9: 45734 | CI9: 45735 | CJ9: 45736 | CK9: 45737 | CL9: 45738 | CM9: 45739 | CN9: 45740 | CO9: 45741 | CP9: 45742 | CQ9: 45743 | CR9: 45744 | CS9: 45745 | CT9: 45746 | CU9: 45747 | CV9: 45748 | CW9: 45749 | CX9: 45750 | CY9: 45751 | CZ9: 45752 | DA9: 45753 | DB9: 45754 | DC9: 45755 | DD9: 45756 | DE9: 45757 | DF9: 45758 | DG9: 45759 | DH9: 45760 | DI9: 45761 | DJ9: 45762 | DK9: 45763 | DL9: 45764 | DM9: 45765 | DN9: 45766 | DO9: 45767 | DP9: 45768 | DQ9: 45769 | DR9: 45770 | DS9: 45771 | DT9: 45772 | DU9: 45773 | DV9: 45774 | DW9: 45775 | DX9: 45776 | DY9: 45777 | DZ9: 45778 | EA9: 45779 | EB9: 45780 | EC9: 45781 | ED9: 45782 | EE9: 45783 | EF9: 45784 | EG9: 45785 | EH9: 45786 | EI9: 45787 | EJ9: 45788 | EK9: 45789 | EL9: 45790 | EM9: 45791 | EN9: 45792 | EO9: 45793 | EP9: 45794 | EQ9: 45795 | ER9: 45796 | ES9: 45797 | ET9: 45798 | EU9: 45799 | EV9: 45800 | EW9: 45801 | EX9: 45802 | EY9: 45803 | EZ9: 45804 | FA9: 45805 | FB9: 45806 | FC9: 45807 | FD9: 45808 | FE9: 45809 | FF9: 45810 | FG9: 45811 | FH9: 45812 | FI9: 45813 | FJ9: 45814 | FK9: 45815 | FL9: 45816 | FM9: 45817 | FN9: 45818 | FO9: 45819 | FP9: 45820 | FQ9: 45821 | FR9: 45822 | FS9: 45823 | FT9: 45824 | FU9: 45825 | FV9: 45826 | FW9: 45827 | FX9: 45828 | FY9: 45829 | FZ9: 45830 | GA9: 45831 | GB9: 45832 | GC9: 45833 | GD9: 45834 | GE9: 45835 | GF9: 45836 | GG9: 45837 | GH9: 45838 | GI9: 45839 | GJ9: 45840 | GK9: 45841 | GL9: 45842 | GM9: 45843 | GN9: 45844 | GO9: 45845 | GP9: 45846 | GQ9: 45847 | GR9: 45848 | GS9: 45849 | GT9: 45850 | GU9: 45851 | GV9: 45852 | GW9: 45853 | GX9: 45854 | GY9: 45855 | GZ9: 45856 | HA9: 45857 | HB9: 45858 | HC9: 45859 | HD9: 45860 | HE9: 45861 | HF9: 45862 | HG9: 45863 | HH9: 45864 | HI9: 45865 | HJ9: 45866 | HK9: 45867 | HL9: 45868 | HM9: 45869 | HN9: 45870 | HO9: 45871 | HP9: 45872 | HQ9: 45873 | HR9: 45874 | HS9: 45875 | HT9: 45876 | HU9: 45877 | HV9: 45878 | HW9: 45879 | HX9: 45880 | HY9: 45881 | HZ9: 45882 | IA9: 45883 | IB9: 45884 | IC9: 45885 | ID9: 45886 | IE9: 45887 | IF9: 45888 | IG9: 45889 | IH9: 45890 | II9: 45891 | IJ9: 45892 | IK9: 45893 | IL9: 45894 | IM9: 45895 | IN9: 45896 | IO9: 45897 | IP9: 45898 | IQ9: 45899 | IR9: 45900 | IS9: 45901 | IT9: 45902 | IU9: 45903 | IV9: 45904 | IW9: 45905 | IX9: 45906 | IY9: 45907 | IZ9: 45908 | JA9: 45909 | JB9: 45910 | JC9: 45911 | JD9: 45912 | JE9: 45913 | JF9: 45914 | JG9: 45915 | JH9: 45916 | JI9: 45917 | JJ9: 45918 | JK9: 45919 | JL9: 45920 | JM9: 45921 | JN9: 45922 | JO9: 45923 | JP9: 45924 | JQ9: 45925 | JR9: 45926 | JS9: 45927 | JT9: 45928 | JU9: 45929 | JV9: 45930 | JW9: 45931 | JX9: 45932 | JY9: 45933 | JZ9: 45934 | KA9: 45935 | KB9: 45936 | KC9: 45937 | KD9: 45938 | KE9: 45939 | KF9: 45940 | KG9: 45941 | KH9: 45942 | KI9: 45943 | KJ9: 45944 | KK9: 45945 | KL9: 45946 | KM9: 45947 | KN9: 45948 | KO9: 45949 | KP9: 45950 | KQ9: 45951 | KR9: 45952 | KS9: 45953 | KT9: 45954 | KU9: 45955 | KV9: 45956 | KW9: 45957 | KX9: 45958 | KY9: 45959 | KZ9: 45960 | LA9: 45961 | LB9: 45962 | LC9: 45963 | LD9: 45964 | LE9: 45965 | LF9: 45966 | LG9: 45967 | LH9: 45968 | LI9: 45969 | LJ9: 45970 | LK9: 45971 | LL9: 45972 | LM9: 45973 | LN9: 45974 | LO9: 45975 | LP9: 45976 | LQ9: 45977 | LR9: 45978 | LS9: 45979 | LT9: 45980 | LU9: 45981 | LV9: 45982 | LW9: 45983 | LX9: 45984 | LY9: 45985 | LZ9: 45986 | MA9: 45987 | MB9: 45988 | MC9: 45989 | MD9: 45990 | ME9: 45991 | MF9: 45992 | MG9: 45993 | MH9: 45994 | MI9: 45995 | MJ9: 45996 | MK9: 45997 | ML9: 45998 | MM9: 45999 | MN9: 46000 | MO9: 46001 | MP9: 46002 | MQ9: 46003 | MR9: 46004 | MS9: 46005 | MT9: 46006 | MU9: 46007 | MV9: 46008 | MW9: 46009 | MX9: 46010 | MY9: 46011 | MZ9: 46012 | NA9: 46013 | NB9: 46014 | NC9: 46015 | ND9: 46016 | NE9: 46017 | NF9: 46018 | NG9: 46019 | NH9: 46020 | NI9: 46021 | NJ9: 46022
D11: 45292 | E11: 45293 | F11: =(E11-D11)+1 -> 2 | H11: PENDENTE
F12: =(E12-D12)+1 -> 1 | H12: PENDENTE
F13: =(E13-D13)+1 -> 1 | H13: PENDENTE
F14: =(E14-D14)+1 -> 1 | H14: PENDENTE
F15: =(E15-D15)+1 -> 1 | H15: PENDENTE
F16: =(E16-D16)+1 -> 1 | H16: PENDENTE
F17: =(E17-D17)+1 -> 1 | H17: PENDENTE
F18: =(E18-D18)+1 -> 1 | H18: PENDENTE
F19: =(E19-D19)+1 -> 1 | H19: PENDENTE
F20: =(E20-D20)+1 -> 1 | H20: PENDENTE
F21: =(E21-D21)+1 -> 1 | H21: PENDENTE
F22: =(E22-D22)+1 -> 1 | H22: PENDENTE
F23: =(E23-D23)+1 -> 1 | H23: PENDENTE
... F40: =(E40-D40)+1 -> 1 | H40: PENDENTE
